Compiled from "ResolverHandler.java"
public class com.minecolonies.core.colony.requestsystem.management.handlers.ResolverHandler implements com.minecolonies.api.colony.requestsystem.management.IResolverHandler {
  public com.minecolonies.core.colony.requestsystem.management.handlers.ResolverHandler(com.minecolonies.core.colony.requestsystem.management.IStandardRequestManager);
    Code:
       0: aload_0
       1: invokespecial #1                  // Method java/lang/Object."<init>":()V
       4: aload_0
       5: new           #7                  // class java/util/ArrayList
       8: dup
       9: invokespecial #9                  // Method java/util/ArrayList."<init>":()V
      12: putfield      #10                 // Field tempBlackList:Ljava/util/List;
      15: aload_0
      16: aload_1
      17: putfield      #16                 // Field manager:Lcom/minecolonies/core/colony/requestsystem/management/IStandardRequestManager;
      20: return

  public com.minecolonies.api.colony.requestsystem.manager.IRequestManager getManager();
    Code:
       0: aload_0
       1: getfield      #16                 // Field manager:Lcom/minecolonies/core/colony/requestsystem/management/IStandardRequestManager;
       4: areturn

  public java.util.Collection<com.minecolonies.api.colony.requestsystem.token.IToken<?>> registerResolvers(com.minecolonies.api.colony.requestsystem.resolver.IRequestResolver<?>...);
    Code:
       0: aload_1
       1: invokestatic  #20                 // Method java/util/Arrays.stream:([Ljava/lang/Object;)Ljava/util/stream/Stream;
       4: aload_0
       5: invokedynamic #26,  0             // InvokeDynamic #0:apply:(Lcom/minecolonies/core/colony/requestsystem/management/handlers/ResolverHandler;)Ljava/util/function/Function;
      10: invokeinterface #30,  2           // InterfaceMethod java/util/stream/Stream.map:(Ljava/util/function/Function;)Ljava/util/stream/Stream;
      15: invokestatic  #36                 // Method java/util/stream/Collectors.toList:()Ljava/util/stream/Collector;
      18: invokeinterface #42,  2           // InterfaceMethod java/util/stream/Stream.collect:(Ljava/util/stream/Collector;)Ljava/lang/Object;
      23: checkcast     #46                 // class java/util/Collection
      26: areturn

  public com.minecolonies.api.colony.requestsystem.token.IToken<?> registerResolver(com.minecolonies.api.colony.requestsystem.resolver.IRequestResolver<? extends com.minecolonies.api.colony.requestsystem.requestable.IRequestable>);
    Code:
       0: aload_0
       1: getfield      #16                 // Field manager:Lcom/minecolonies/core/colony/requestsystem/management/IStandardRequestManager;
       4: invokeinterface #48,  1           // InterfaceMethod com/minecolonies/core/colony/requestsystem/management/IStandardRequestManager.getRequestResolverIdentitiesDataStore:()Lcom/minecolonies/api/colony/requestsystem/data/IRequestResolverIdentitiesDataStore;
       9: invokeinterface #54,  1           // InterfaceMethod com/minecolonies/api/colony/requestsystem/data/IRequestResolverIdentitiesDataStore.getIdentities:()Lcom/google/common/collect/BiMap;
      14: aload_1
      15: invokeinterface #60,  1           // InterfaceMethod com/minecolonies/api/colony/requestsystem/resolver/IRequestResolver.getId:()Lcom/minecolonies/api/colony/requestsystem/token/IToken;
      20: invokeinterface #66,  2           // InterfaceMethod com/google/common/collect/BiMap.containsKey:(Ljava/lang/Object;)Z
      25: ifeq          38
      28: new           #72                 // class java/lang/IllegalArgumentException
      31: dup
      32: ldc           #74                 // String The token attached to this resolver is already registered. Cannot register twice!
      34: invokespecial #76                 // Method java/lang/IllegalArgumentException."<init>":(Ljava/lang/String;)V
      37: athrow
      38: aload_0
      39: getfield      #16                 // Field manager:Lcom/minecolonies/core/colony/requestsystem/management/IStandardRequestManager;
      42: invokeinterface #48,  1           // InterfaceMethod com/minecolonies/core/colony/requestsystem/management/IStandardRequestManager.getRequestResolverIdentitiesDataStore:()Lcom/minecolonies/api/colony/requestsystem/data/IRequestResolverIdentitiesDataStore;
      47: invokeinterface #54,  1           // InterfaceMethod com/minecolonies/api/colony/requestsystem/data/IRequestResolverIdentitiesDataStore.getIdentities:()Lcom/google/common/collect/BiMap;
      52: aload_1
      53: invokeinterface #79,  2           // InterfaceMethod com/google/common/collect/BiMap.containsValue:(Ljava/lang/Object;)Z
      58: ifeq          71
      61: new           #72                 // class java/lang/IllegalArgumentException
      64: dup
      65: ldc           #82                 // String The given resolver is already registered with a different token. Cannot register twice!
      67: invokespecial #76                 // Method java/lang/IllegalArgumentException."<init>":(Ljava/lang/String;)V
      70: athrow
      71: aload_0
      72: getfield      #16                 // Field manager:Lcom/minecolonies/core/colony/requestsystem/management/IStandardRequestManager;
      75: invokeinterface #48,  1           // InterfaceMethod com/minecolonies/core/colony/requestsystem/management/IStandardRequestManager.getRequestResolverIdentitiesDataStore:()Lcom/minecolonies/api/colony/requestsystem/data/IRequestResolverIdentitiesDataStore;
      80: invokeinterface #54,  1           // InterfaceMethod com/minecolonies/api/colony/requestsystem/data/IRequestResolverIdentitiesDataStore.getIdentities:()Lcom/google/common/collect/BiMap;
      85: aload_1
      86: invokeinterface #60,  1           // InterfaceMethod com/minecolonies/api/colony/requestsystem/resolver/IRequestResolver.getId:()Lcom/minecolonies/api/colony/requestsystem/token/IToken;
      91: aload_1
      92: invokeinterface #84,  3           // InterfaceMethod com/google/common/collect/BiMap.put:(Ljava/lang/Object;Ljava/lang/Object;)Ljava/lang/Object;
      97: pop
      98: aload_1
      99: invokeinterface #88,  1           // InterfaceMethod com/minecolonies/api/colony/requestsystem/resolver/IRequestResolver.getRequestType:()Lcom/google/common/reflect/TypeToken;
     104: invokestatic  #92                 // Method com/minecolonies/api/util/ReflectionUtils.getSuperClasses:(Lcom/google/common/reflect/TypeToken;)Ljava/util/Set;
     107: astore_2
     108: aload_2
     109: getstatic     #98                 // Field com/minecolonies/api/util/constant/TypeConstants.OBJECT:Lcom/google/common/reflect/TypeToken;
     112: invokeinterface #104,  2          // InterfaceMethod java/util/Set.remove:(Ljava/lang/Object;)Z
     117: pop
     118: aload_2
     119: aload_0
     120: aload_1
     121: invokedynamic #109,  0            // InvokeDynamic #1:accept:(Lcom/minecolonies/core/colony/requestsystem/management/handlers/ResolverHandler;Lcom/minecolonies/api/colony/requestsystem/resolver/IRequestResolver;)Ljava/util/function/Consumer;
     126: invokeinterface #113,  2          // InterfaceMethod java/util/Set.forEach:(Ljava/util/function/Consumer;)V
     131: aload_1
     132: invokeinterface #60,  1           // InterfaceMethod com/minecolonies/api/colony/requestsystem/resolver/IRequestResolver.getId:()Lcom/minecolonies/api/colony/requestsystem/token/IToken;
     137: areturn

  public java.util.Collection<com.minecolonies.api.colony.requestsystem.token.IToken<?>> registerResolvers(java.util.Collection<com.minecolonies.api.colony.requestsystem.resolver.IRequestResolver<?>>);
    Code:
       0: aload_1
       1: invokeinterface #117,  1          // InterfaceMethod java/util/Collection.stream:()Ljava/util/stream/Stream;
       6: aload_0
       7: invokedynamic #26,  0             // InvokeDynamic #0:apply:(Lcom/minecolonies/core/colony/requestsystem/management/handlers/ResolverHandler;)Ljava/util/function/Function;
      12: invokeinterface #30,  2           // InterfaceMethod java/util/stream/Stream.map:(Ljava/util/function/Function;)Ljava/util/stream/Stream;
      17: invokestatic  #36                 // Method java/util/stream/Collectors.toList:()Ljava/util/stream/Collector;
      20: invokeinterface #42,  2           // InterfaceMethod java/util/stream/Stream.collect:(Ljava/util/stream/Collector;)Ljava/lang/Object;
      25: checkcast     #46                 // class java/util/Collection
      28: areturn

  public void removeResolver(com.minecolonies.api.colony.requestsystem.token.IToken<?>);
    Code:
       0: aload_0
       1: getfield      #16                 // Field manager:Lcom/minecolonies/core/colony/requestsystem/management/IStandardRequestManager;
       4: invokeinterface #48,  1           // InterfaceMethod com/minecolonies/core/colony/requestsystem/management/IStandardRequestManager.getRequestResolverIdentitiesDataStore:()Lcom/minecolonies/api/colony/requestsystem/data/IRequestResolverIdentitiesDataStore;
       9: invokeinterface #54,  1           // InterfaceMethod com/minecolonies/api/colony/requestsystem/data/IRequestResolverIdentitiesDataStore.getIdentities:()Lcom/google/common/collect/BiMap;
      14: aload_1
      15: invokeinterface #66,  2           // InterfaceMethod com/google/common/collect/BiMap.containsKey:(Ljava/lang/Object;)Z
      20: ifne          33
      23: new           #72                 // class java/lang/IllegalArgumentException
      26: dup
      27: ldc           #120                // String The token is unknown to this manager.
      29: invokespecial #76                 // Method java/lang/IllegalArgumentException."<init>":(Ljava/lang/String;)V
      32: athrow
      33: aload_0
      34: aload_0
      35: aload_1
      36: invokevirtual #122                // Method getResolver:(Lcom/minecolonies/api/colony/requestsystem/token/IToken;)Lcom/minecolonies/api/colony/requestsystem/resolver/IRequestResolver;
      39: invokevirtual #126                // Method removeResolver:(Lcom/minecolonies/api/colony/requestsystem/resolver/IRequestResolver;)V
      42: return

  public void removeResolver(com.minecolonies.api.colony.requestsystem.resolver.IRequestResolver<?>);
    Code:
       0: aload_0
       1: aload_1
       2: invokeinterface #60,  1           // InterfaceMethod com/minecolonies/api/colony/requestsystem/resolver/IRequestResolver.getId:()Lcom/minecolonies/api/colony/requestsystem/token/IToken;
       7: invokevirtual #122                // Method getResolver:(Lcom/minecolonies/api/colony/requestsystem/token/IToken;)Lcom/minecolonies/api/colony/requestsystem/resolver/IRequestResolver;
      10: astore_2
      11: aload_2
      12: aload_1
      13: invokeinterface #130,  2          // InterfaceMethod com/minecolonies/api/colony/requestsystem/resolver/IRequestResolver.equals:(Ljava/lang/Object;)Z
      18: ifne          31
      21: new           #72                 // class java/lang/IllegalArgumentException
      24: dup
      25: ldc           #133                // String The given resolver and the resolver that is registered with its token are not the same.
      27: invokespecial #76                 // Method java/lang/IllegalArgumentException."<init>":(Ljava/lang/String;)V
      30: athrow
      31: aload_0
      32: getfield      #16                 // Field manager:Lcom/minecolonies/core/colony/requestsystem/management/IStandardRequestManager;
      35: invokeinterface #135,  1          // InterfaceMethod com/minecolonies/core/colony/requestsystem/management/IStandardRequestManager.getRequestResolverRequestAssignmentDataStore:()Lcom/minecolonies/api/colony/requestsystem/data/IRequestResolverRequestAssignmentDataStore;
      40: invokeinterface #139,  1          // InterfaceMethod com/minecolonies/api/colony/requestsystem/data/IRequestResolverRequestAssignmentDataStore.getAssignments:()Ljava/util/Map;
      45: aload_2
      46: invokeinterface #60,  1           // InterfaceMethod com/minecolonies/api/colony/requestsystem/resolver/IRequestResolver.getId:()Lcom/minecolonies/api/colony/requestsystem/token/IToken;
      51: invokeinterface #145,  2          // InterfaceMethod java/util/Map.containsKey:(Ljava/lang/Object;)Z
      56: ifeq          105
      59: aload_0
      60: getfield      #16                 // Field manager:Lcom/minecolonies/core/colony/requestsystem/management/IStandardRequestManager;
      63: invokeinterface #135,  1          // InterfaceMethod com/minecolonies/core/colony/requestsystem/management/IStandardRequestManager.getRequestResolverRequestAssignmentDataStore:()Lcom/minecolonies/api/colony/requestsystem/data/IRequestResolverRequestAssignmentDataStore;
      68: invokeinterface #139,  1          // InterfaceMethod com/minecolonies/api/colony/requestsystem/data/IRequestResolverRequestAssignmentDataStore.getAssignments:()Ljava/util/Map;
      73: aload_2
      74: invokeinterface #60,  1           // InterfaceMethod com/minecolonies/api/colony/requestsystem/resolver/IRequestResolver.getId:()Lcom/minecolonies/api/colony/requestsystem/token/IToken;
      79: invokeinterface #148,  2          // InterfaceMethod java/util/Map.get:(Ljava/lang/Object;)Ljava/lang/Object;
      84: checkcast     #46                 // class java/util/Collection
      87: invokeinterface #152,  1          // InterfaceMethod java/util/Collection.isEmpty:()Z
      92: ifne          105
      95: new           #72                 // class java/lang/IllegalArgumentException
      98: dup
      99: ldc           #156                // String Cannot remove a resolver that is still in use. Reassign all registered requests before removing
     101: invokespecial #76                 // Method java/lang/IllegalArgumentException."<init>":(Ljava/lang/String;)V
     104: athrow
     105: aload_0
     106: aload_1
     107: invokevirtual #158                // Method removeResolverInternal:(Lcom/minecolonies/api/colony/requestsystem/resolver/IRequestResolver;)V
     110: return

  public void processResolverForRemoval(java.util.Collection<com.minecolonies.api.colony.requestsystem.token.IToken<?>>, com.minecolonies.api.colony.requestsystem.token.IToken<?>);
    Code:
       0: aload_1
       1: aload_2
       2: invokeinterface #161,  2          // InterfaceMethod java/util/Collection.contains:(Ljava/lang/Object;)Z
       7: invokestatic  #164                // Method org/apache/commons/lang3/Validate.isTrue:(Z)V
      10: aload_0
      11: getfield      #16                 // Field manager:Lcom/minecolonies/core/colony/requestsystem/management/IStandardRequestManager;
      14: invokeinterface #135,  1          // InterfaceMethod com/minecolonies/core/colony/requestsystem/management/IStandardRequestManager.getRequestResolverRequestAssignmentDataStore:()Lcom/minecolonies/api/colony/requestsystem/data/IRequestResolverRequestAssignmentDataStore;
      19: invokeinterface #139,  1          // InterfaceMethod com/minecolonies/api/colony/requestsystem/data/IRequestResolverRequestAssignmentDataStore.getAssignments:()Ljava/util/Map;
      24: aload_2
      25: invokeinterface #145,  2          // InterfaceMethod java/util/Map.containsKey:(Ljava/lang/Object;)Z
      30: ifeq          64
      33: aload_0
      34: getfield      #16                 // Field manager:Lcom/minecolonies/core/colony/requestsystem/management/IStandardRequestManager;
      37: invokeinterface #135,  1          // InterfaceMethod com/minecolonies/core/colony/requestsystem/management/IStandardRequestManager.getRequestResolverRequestAssignmentDataStore:()Lcom/minecolonies/api/colony/requestsystem/data/IRequestResolverRequestAssignmentDataStore;
      42: invokeinterface #139,  1          // InterfaceMethod com/minecolonies/api/colony/requestsystem/data/IRequestResolverRequestAssignmentDataStore.getAssignments:()Ljava/util/Map;
      47: aload_2
      48: invokeinterface #148,  2          // InterfaceMethod java/util/Map.get:(Ljava/lang/Object;)Ljava/lang/Object;
      53: checkcast     #46                 // class java/util/Collection
      56: invokeinterface #152,  1          // InterfaceMethod java/util/Collection.isEmpty:()Z
      61: ifeq          70
      64: aload_0
      65: aload_2
      66: invokevirtual #170                // Method removeResolverWithoutAssignedRequests:(Lcom/minecolonies/api/colony/requestsystem/token/IToken;)V
      69: return
      70: aload_0
      71: aload_1
      72: aload_2
      73: invokevirtual #174                // Method removeResolverWithAssignedRequests:(Ljava/util/Collection;Lcom/minecolonies/api/colony/requestsystem/token/IToken;)V
      76: return

  void removeResolverWithoutAssignedRequests(com.minecolonies.api.colony.requestsystem.token.IToken<?>);
    Code:
       0: aload_0
       1: getfield      #16                 // Field manager:Lcom/minecolonies/core/colony/requestsystem/management/IStandardRequestManager;
       4: aload_1
       5: invokestatic  #178                // Method java/lang/String.valueOf:(Ljava/lang/Object;)Ljava/lang/String;
       8: invokedynamic #184,  0            // InvokeDynamic #2:makeConcatWithConstants:(Ljava/lang/String;)Ljava/lang/String;
      13: invokeinterface #188,  2          // InterfaceMethod com/minecolonies/core/colony/requestsystem/management/IStandardRequestManager.log:(Ljava/lang/String;)V
      18: aload_0
      19: getfield      #16                 // Field manager:Lcom/minecolonies/core/colony/requestsystem/management/IStandardRequestManager;
      22: invokeinterface #135,  1          // InterfaceMethod com/minecolonies/core/colony/requestsystem/management/IStandardRequestManager.getRequestResolverRequestAssignmentDataStore:()Lcom/minecolonies/api/colony/requestsystem/data/IRequestResolverRequestAssignmentDataStore;
      27: invokeinterface #139,  1          // InterfaceMethod com/minecolonies/api/colony/requestsystem/data/IRequestResolverRequestAssignmentDataStore.getAssignments:()Ljava/util/Map;
      32: aload_1
      33: invokeinterface #191,  2          // InterfaceMethod java/util/Map.remove:(Ljava/lang/Object;)Ljava/lang/Object;
      38: pop
      39: aload_0
      40: getfield      #16                 // Field manager:Lcom/minecolonies/core/colony/requestsystem/management/IStandardRequestManager;
      43: invokeinterface #193,  1          // InterfaceMethod com/minecolonies/core/colony/requestsystem/management/IStandardRequestManager.getResolverHandler:()Lcom/minecolonies/api/colony/requestsystem/management/IResolverHandler;
      48: aload_1
      49: invokeinterface #197,  2          // InterfaceMethod com/minecolonies/api/colony/requestsystem/management/IResolverHandler.removeResolver:(Lcom/minecolonies/api/colony/requestsystem/token/IToken;)V
      54: return

  void removeResolverWithAssignedRequests(java.util.Collection<com.minecolonies.api.colony.requestsystem.token.IToken<?>>, com.minecolonies.api.colony.requestsystem.token.IToken<?>);
    Code:
       0: aload_1
       1: aload_2
       2: invokeinterface #161,  2          // InterfaceMethod java/util/Collection.contains:(Ljava/lang/Object;)Z
       7: invokestatic  #164                // Method org/apache/commons/lang3/Validate.isTrue:(Z)V
      10: new           #7                  // class java/util/ArrayList
      13: dup
      14: aload_0
      15: getfield      #16                 // Field manager:Lcom/minecolonies/core/colony/requestsystem/management/IStandardRequestManager;
      18: invokeinterface #135,  1          // InterfaceMethod com/minecolonies/core/colony/requestsystem/management/IStandardRequestManager.getRequestResolverRequestAssignmentDataStore:()Lcom/minecolonies/api/colony/requestsystem/data/IRequestResolverRequestAssignmentDataStore;
      23: invokeinterface #139,  1          // InterfaceMethod com/minecolonies/api/colony/requestsystem/data/IRequestResolverRequestAssignmentDataStore.getAssignments:()Ljava/util/Map;
      28: aload_2
      29: invokeinterface #148,  2          // InterfaceMethod java/util/Map.get:(Ljava/lang/Object;)Ljava/lang/Object;
      34: checkcast     #46                 // class java/util/Collection
      37: invokespecial #201                // Method java/util/ArrayList."<init>":(Ljava/util/Collection;)V
      40: astore_3
      41: aload_0
      42: getfield      #16                 // Field manager:Lcom/minecolonies/core/colony/requestsystem/management/IStandardRequestManager;
      45: aload_2
      46: invokestatic  #178                // Method java/lang/String.valueOf:(Ljava/lang/Object;)Ljava/lang/String;
      49: invokedynamic #204,  0            // InvokeDynamic #3:makeConcatWithConstants:(Ljava/lang/String;)Ljava/lang/String;
      54: invokeinterface #188,  2          // InterfaceMethod com/minecolonies/core/colony/requestsystem/management/IStandardRequestManager.log:(Ljava/lang/String;)V
      59: aload_0
      60: getfield      #10                 // Field tempBlackList:Ljava/util/List;
      63: aload_1
      64: invokeinterface #205,  2          // InterfaceMethod java/util/List.addAll:(Ljava/util/Collection;)Z
      69: pop
      70: aload_3
      71: invokeinterface #211,  1          // InterfaceMethod java/util/Collection.iterator:()Ljava/util/Iterator;
      76: astore        4
      78: aload         4
      80: invokeinterface #215,  1          // InterfaceMethod java/util/Iterator.hasNext:()Z
      85: ifeq          169
      88: aload         4
      90: invokeinterface #220,  1          // InterfaceMethod java/util/Iterator.next:()Ljava/lang/Object;
      95: checkcast     #224                // class com/minecolonies/api/colony/requestsystem/token/IToken
      98: astore        5
     100: aload_0
     101: getfield      #16                 // Field manager:Lcom/minecolonies/core/colony/requestsystem/management/IStandardRequestManager;
     104: aload         5
     106: invokeinterface #226,  2          // InterfaceMethod com/minecolonies/core/colony/requestsystem/management/IStandardRequestManager.getRequestForToken:(Lcom/minecolonies/api/colony/requestsystem/token/IToken;)Lcom/minecolonies/api/colony/requestsystem/request/IRequest;
     111: astore        6
     113: aload         6
     115: invokeinterface #230,  1          // InterfaceMethod com/minecolonies/api/colony/requestsystem/request/IRequest.getChildren:()Lcom/google/common/collect/ImmutableCollection;
     120: invokevirtual #236                // Method com/google/common/collect/ImmutableCollection.iterator:()Lcom/google/common/collect/UnmodifiableIterator;
     123: astore        7
     125: aload         7
     127: invokeinterface #215,  1          // InterfaceMethod java/util/Iterator.hasNext:()Z
     132: ifeq          166
     135: aload         7
     137: invokeinterface #220,  1          // InterfaceMethod java/util/Iterator.next:()Ljava/lang/Object;
     142: checkcast     #224                // class com/minecolonies/api/colony/requestsystem/token/IToken
     145: astore        8
     147: aload_0
     148: getfield      #16                 // Field manager:Lcom/minecolonies/core/colony/requestsystem/management/IStandardRequestManager;
     151: invokeinterface #241,  1          // InterfaceMethod com/minecolonies/core/colony/requestsystem/management/IStandardRequestManager.getRequestHandler:()Lcom/minecolonies/api/colony/requestsystem/management/IRequestHandler;
     156: aload         8
     158: invokeinterface #245,  2          // InterfaceMethod com/minecolonies/api/colony/requestsystem/management/IRequestHandler.onRequestCancelledDirectly:(Lcom/minecolonies/api/colony/requestsystem/token/IToken;)V
     163: goto          125
     166: goto          78
     169: new           #7                  // class java/util/ArrayList
     172: dup
     173: aload_0
     174: getfield      #16                 // Field manager:Lcom/minecolonies/core/colony/requestsystem/management/IStandardRequestManager;
     177: invokeinterface #135,  1          // InterfaceMethod com/minecolonies/core/colony/requestsystem/management/IStandardRequestManager.getRequestResolverRequestAssignmentDataStore:()Lcom/minecolonies/api/colony/requestsystem/data/IRequestResolverRequestAssignmentDataStore;
     182: invokeinterface #139,  1          // InterfaceMethod com/minecolonies/api/colony/requestsystem/data/IRequestResolverRequestAssignmentDataStore.getAssignments:()Ljava/util/Map;
     187: aload_2
     188: invokeinterface #148,  2          // InterfaceMethod java/util/Map.get:(Ljava/lang/Object;)Ljava/lang/Object;
     193: checkcast     #46                 // class java/util/Collection
     196: invokespecial #201                // Method java/util/ArrayList."<init>":(Ljava/util/Collection;)V
     199: astore_3
     200: aload_3
     201: invokeinterface #211,  1          // InterfaceMethod java/util/Collection.iterator:()Ljava/util/Iterator;
     206: astore        4
     208: aload         4
     210: invokeinterface #215,  1          // InterfaceMethod java/util/Iterator.hasNext:()Z
     215: ifeq          246
     218: aload         4
     220: invokeinterface #220,  1          // InterfaceMethod java/util/Iterator.next:()Ljava/lang/Object;
     225: checkcast     #224                // class com/minecolonies/api/colony/requestsystem/token/IToken
     228: astore        5
     230: aload_0
     231: getfield      #16                 // Field manager:Lcom/minecolonies/core/colony/requestsystem/management/IStandardRequestManager;
     234: aload         5
     236: aload_1
     237: invokeinterface #250,  3          // InterfaceMethod com/minecolonies/core/colony/requestsystem/management/IStandardRequestManager.reassignRequest:(Lcom/minecolonies/api/colony/requestsystem/token/IToken;Ljava/util/Collection;)Lcom/minecolonies/api/colony/requestsystem/token/IToken;
     242: pop
     243: goto          208
     246: aload_0
     247: getfield      #10                 // Field tempBlackList:Ljava/util/List;
     250: aload_1
     251: invokeinterface #254,  2          // InterfaceMethod java/util/List.removeAll:(Ljava/util/Collection;)Z
     256: pop
     257: aload_0
     258: aload_2
     259: invokevirtual #170                // Method removeResolverWithoutAssignedRequests:(Lcom/minecolonies/api/colony/requestsystem/token/IToken;)V
     262: aload_0
     263: getfield      #16                 // Field manager:Lcom/minecolonies/core/colony/requestsystem/management/IStandardRequestManager;
     266: aload_2
     267: invokestatic  #178                // Method java/lang/String.valueOf:(Ljava/lang/Object;)Ljava/lang/String;
     270: invokedynamic #257,  0            // InvokeDynamic #4:makeConcatWithConstants:(Ljava/lang/String;)Ljava/lang/String;
     275: invokeinterface #188,  2          // InterfaceMethod com/minecolonies/core/colony/requestsystem/management/IStandardRequestManager.log:(Ljava/lang/String;)V
     280: return

  public java.util.Collection<com.minecolonies.api.colony.requestsystem.token.IToken<?>> getRequestsAssignedToResolver(com.minecolonies.api.colony.requestsystem.resolver.IRequestResolver<?>);
    Code:
       0: aload_0
       1: getfield      #16                 // Field manager:Lcom/minecolonies/core/colony/requestsystem/management/IStandardRequestManager;
       4: invokeinterface #135,  1          // InterfaceMethod com/minecolonies/core/colony/requestsystem/management/IStandardRequestManager.getRequestResolverRequestAssignmentDataStore:()Lcom/minecolonies/api/colony/requestsystem/data/IRequestResolverRequestAssignmentDataStore;
       9: invokeinterface #139,  1          // InterfaceMethod com/minecolonies/api/colony/requestsystem/data/IRequestResolverRequestAssignmentDataStore.getAssignments:()Ljava/util/Map;
      14: aload_1
      15: invokeinterface #60,  1           // InterfaceMethod com/minecolonies/api/colony/requestsystem/resolver/IRequestResolver.getId:()Lcom/minecolonies/api/colony/requestsystem/token/IToken;
      20: invokeinterface #145,  2          // InterfaceMethod java/util/Map.containsKey:(Ljava/lang/Object;)Z
      25: ifeq          57
      28: aload_0
      29: getfield      #16                 // Field manager:Lcom/minecolonies/core/colony/requestsystem/management/IStandardRequestManager;
      32: invokeinterface #135,  1          // InterfaceMethod com/minecolonies/core/colony/requestsystem/management/IStandardRequestManager.getRequestResolverRequestAssignmentDataStore:()Lcom/minecolonies/api/colony/requestsystem/data/IRequestResolverRequestAssignmentDataStore;
      37: invokeinterface #139,  1          // InterfaceMethod com/minecolonies/api/colony/requestsystem/data/IRequestResolverRequestAssignmentDataStore.getAssignments:()Ljava/util/Map;
      42: aload_1
      43: invokeinterface #60,  1           // InterfaceMethod com/minecolonies/api/colony/requestsystem/resolver/IRequestResolver.getId:()Lcom/minecolonies/api/colony/requestsystem/token/IToken;
      48: invokeinterface #148,  2          // InterfaceMethod java/util/Map.get:(Ljava/lang/Object;)Ljava/lang/Object;
      53: checkcast     #46                 // class java/util/Collection
      56: areturn
      57: invokestatic  #258                // Method com/google/common/collect/Lists.newArrayList:()Ljava/util/ArrayList;
      60: areturn

  public com.minecolonies.api.colony.requestsystem.resolver.IRequestResolver<? extends com.minecolonies.api.colony.requestsystem.requestable.IRequestable> getResolver(com.minecolonies.api.colony.requestsystem.token.IToken<?>);
    Code:
       0: aload_0
       1: getfield      #16                 // Field manager:Lcom/minecolonies/core/colony/requestsystem/management/IStandardRequestManager;
       4: invokeinterface #48,  1           // InterfaceMethod com/minecolonies/core/colony/requestsystem/management/IStandardRequestManager.getRequestResolverIdentitiesDataStore:()Lcom/minecolonies/api/colony/requestsystem/data/IRequestResolverIdentitiesDataStore;
       9: invokeinterface #54,  1           // InterfaceMethod com/minecolonies/api/colony/requestsystem/data/IRequestResolverIdentitiesDataStore.getIdentities:()Lcom/google/common/collect/BiMap;
      14: aload_1
      15: invokeinterface #66,  2           // InterfaceMethod com/google/common/collect/BiMap.containsKey:(Ljava/lang/Object;)Z
      20: ifne          34
      23: new           #72                 // class java/lang/IllegalArgumentException
      26: dup
      27: ldc_w         #264                // String The given token for a resolver is not known to this manager!
      30: invokespecial #76                 // Method java/lang/IllegalArgumentException."<init>":(Ljava/lang/String;)V
      33: athrow
      34: aload_0
      35: getfield      #16                 // Field manager:Lcom/minecolonies/core/colony/requestsystem/management/IStandardRequestManager;
      38: invokeinterface #48,  1           // InterfaceMethod com/minecolonies/core/colony/requestsystem/management/IStandardRequestManager.getRequestResolverIdentitiesDataStore:()Lcom/minecolonies/api/colony/requestsystem/data/IRequestResolverIdentitiesDataStore;
      43: invokeinterface #54,  1           // InterfaceMethod com/minecolonies/api/colony/requestsystem/data/IRequestResolverIdentitiesDataStore.getIdentities:()Lcom/google/common/collect/BiMap;
      48: aload_1
      49: invokeinterface #266,  2          // InterfaceMethod com/google/common/collect/BiMap.get:(Ljava/lang/Object;)Ljava/lang/Object;
      54: checkcast     #61                 // class com/minecolonies/api/colony/requestsystem/resolver/IRequestResolver
      57: areturn

  public void removeResolverInternal(com.minecolonies.api.colony.requestsystem.resolver.IRequestResolver<?>);
    Code:
       0: aload_0
       1: getfield      #16                 // Field manager:Lcom/minecolonies/core/colony/requestsystem/management/IStandardRequestManager;
       4: invokeinterface #48,  1           // InterfaceMethod com/minecolonies/core/colony/requestsystem/management/IStandardRequestManager.getRequestResolverIdentitiesDataStore:()Lcom/minecolonies/api/colony/requestsystem/data/IRequestResolverIdentitiesDataStore;
       9: invokeinterface #54,  1           // InterfaceMethod com/minecolonies/api/colony/requestsystem/data/IRequestResolverIdentitiesDataStore.getIdentities:()Lcom/google/common/collect/BiMap;
      14: aload_1
      15: invokeinterface #60,  1           // InterfaceMethod com/minecolonies/api/colony/requestsystem/resolver/IRequestResolver.getId:()Lcom/minecolonies/api/colony/requestsystem/token/IToken;
      20: invokeinterface #267,  2          // InterfaceMethod com/google/common/collect/BiMap.remove:(Ljava/lang/Object;)Ljava/lang/Object;
      25: pop
      26: aload_1
      27: invokeinterface #88,  1           // InterfaceMethod com/minecolonies/api/colony/requestsystem/resolver/IRequestResolver.getRequestType:()Lcom/google/common/reflect/TypeToken;
      32: invokestatic  #92                 // Method com/minecolonies/api/util/ReflectionUtils.getSuperClasses:(Lcom/google/common/reflect/TypeToken;)Ljava/util/Set;
      35: astore_2
      36: aload_2
      37: getstatic     #98                 // Field com/minecolonies/api/util/constant/TypeConstants.OBJECT:Lcom/google/common/reflect/TypeToken;
      40: invokeinterface #104,  2          // InterfaceMethod java/util/Set.remove:(Ljava/lang/Object;)Z
      45: pop
      46: aload_2
      47: aload_0
      48: aload_1
      49: invokedynamic #268,  0            // InvokeDynamic #5:accept:(Lcom/minecolonies/core/colony/requestsystem/management/handlers/ResolverHandler;Lcom/minecolonies/api/colony/requestsystem/resolver/IRequestResolver;)Ljava/util/function/Consumer;
      54: invokeinterface #113,  2          // InterfaceMethod java/util/Set.forEach:(Ljava/util/function/Consumer;)V
      59: return

  public void removeResolvers(com.minecolonies.api.colony.requestsystem.resolver.IRequestResolver<?>...);
    Code:
       0: aload_0
       1: aload_1
       2: invokestatic  #269                // Method java/util/Arrays.asList:([Ljava/lang/Object;)Ljava/util/List;
       5: invokevirtual #273                // Method removeResolvers:(Ljava/lang/Iterable;)V
       8: return

  public void removeResolvers(java.lang.Iterable<com.minecolonies.api.colony.requestsystem.resolver.IRequestResolver<?>>);
    Code:
       0: aload_1
       1: aload_0
       2: invokedynamic #277,  0            // InvokeDynamic #6:accept:(Lcom/minecolonies/core/colony/requestsystem/management/handlers/ResolverHandler;)Ljava/util/function/Consumer;
       7: invokeinterface #280,  2          // InterfaceMethod java/lang/Iterable.forEach:(Ljava/util/function/Consumer;)V
      12: return

  public void addRequestToResolver(com.minecolonies.api.colony.requestsystem.resolver.IRequestResolver<?>, com.minecolonies.api.colony.requestsystem.request.IRequest<?>);
    Code:
       0: aload_0
       1: getfield      #16                 // Field manager:Lcom/minecolonies/core/colony/requestsystem/management/IStandardRequestManager;
       4: invokeinterface #135,  1          // InterfaceMethod com/minecolonies/core/colony/requestsystem/management/IStandardRequestManager.getRequestResolverRequestAssignmentDataStore:()Lcom/minecolonies/api/colony/requestsystem/data/IRequestResolverRequestAssignmentDataStore;
       9: invokeinterface #139,  1          // InterfaceMethod com/minecolonies/api/colony/requestsystem/data/IRequestResolverRequestAssignmentDataStore.getAssignments:()Ljava/util/Map;
      14: aload_1
      15: invokeinterface #60,  1           // InterfaceMethod com/minecolonies/api/colony/requestsystem/resolver/IRequestResolver.getId:()Lcom/minecolonies/api/colony/requestsystem/token/IToken;
      20: invokeinterface #145,  2          // InterfaceMethod java/util/Map.containsKey:(Ljava/lang/Object;)Z
      25: ifne          61
      28: aload_0
      29: getfield      #16                 // Field manager:Lcom/minecolonies/core/colony/requestsystem/management/IStandardRequestManager;
      32: invokeinterface #135,  1          // InterfaceMethod com/minecolonies/core/colony/requestsystem/management/IStandardRequestManager.getRequestResolverRequestAssignmentDataStore:()Lcom/minecolonies/api/colony/requestsystem/data/IRequestResolverRequestAssignmentDataStore;
      37: invokeinterface #139,  1          // InterfaceMethod com/minecolonies/api/colony/requestsystem/data/IRequestResolverRequestAssignmentDataStore.getAssignments:()Ljava/util/Map;
      42: aload_1
      43: invokeinterface #60,  1           // InterfaceMethod com/minecolonies/api/colony/requestsystem/resolver/IRequestResolver.getId:()Lcom/minecolonies/api/colony/requestsystem/token/IToken;
      48: new           #283                // class java/util/HashSet
      51: dup
      52: invokespecial #285                // Method java/util/HashSet."<init>":()V
      55: invokeinterface #286,  3          // InterfaceMethod java/util/Map.put:(Ljava/lang/Object;Ljava/lang/Object;)Ljava/lang/Object;
      60: pop
      61: aload_0
      62: getfield      #16                 // Field manager:Lcom/minecolonies/core/colony/requestsystem/management/IStandardRequestManager;
      65: aload_2
      66: invokestatic  #178                // Method java/lang/String.valueOf:(Ljava/lang/Object;)Ljava/lang/String;
      69: aload_1
      70: invokestatic  #178                // Method java/lang/String.valueOf:(Ljava/lang/Object;)Ljava/lang/String;
      73: invokedynamic #287,  0            // InvokeDynamic #7:makeConcatWithConstants:(Ljava/lang/String;Ljava/lang/String;)Ljava/lang/String;
      78: invokeinterface #188,  2          // InterfaceMethod com/minecolonies/core/colony/requestsystem/management/IStandardRequestManager.log:(Ljava/lang/String;)V
      83: aload_0
      84: getfield      #16                 // Field manager:Lcom/minecolonies/core/colony/requestsystem/management/IStandardRequestManager;
      87: invokeinterface #135,  1          // InterfaceMethod com/minecolonies/core/colony/requestsystem/management/IStandardRequestManager.getRequestResolverRequestAssignmentDataStore:()Lcom/minecolonies/api/colony/requestsystem/data/IRequestResolverRequestAssignmentDataStore;
      92: invokeinterface #139,  1          // InterfaceMethod com/minecolonies/api/colony/requestsystem/data/IRequestResolverRequestAssignmentDataStore.getAssignments:()Ljava/util/Map;
      97: aload_1
      98: invokeinterface #60,  1           // InterfaceMethod com/minecolonies/api/colony/requestsystem/resolver/IRequestResolver.getId:()Lcom/minecolonies/api/colony/requestsystem/token/IToken;
     103: invokeinterface #148,  2          // InterfaceMethod java/util/Map.get:(Ljava/lang/Object;)Ljava/lang/Object;
     108: checkcast     #46                 // class java/util/Collection
     111: aload_2
     112: invokeinterface #290,  1          // InterfaceMethod com/minecolonies/api/colony/requestsystem/request/IRequest.getId:()Lcom/minecolonies/api/colony/requestsystem/token/IToken;
     117: invokeinterface #291,  2          // InterfaceMethod java/util/Collection.add:(Ljava/lang/Object;)Z
     122: pop
     123: aload_2
     124: new           #294                // class com/minecolonies/core/colony/requestsystem/management/manager/wrapped/WrappedStaticStateRequestManager
     127: dup
     128: aload_0
     129: getfield      #16                 // Field manager:Lcom/minecolonies/core/colony/requestsystem/management/IStandardRequestManager;
     132: invokespecial #296                // Method com/minecolonies/core/colony/requestsystem/management/manager/wrapped/WrappedStaticStateRequestManager."<init>":(Lcom/minecolonies/core/colony/requestsystem/management/IStandardRequestManager;)V
     135: getstatic     #299                // Field com/minecolonies/api/colony/requestsystem/request/RequestState.ASSIGNED:Lcom/minecolonies/api/colony/requestsystem/request/RequestState;
     138: invokeinterface #305,  3          // InterfaceMethod com/minecolonies/api/colony/requestsystem/request/IRequest.setState:(Lcom/minecolonies/api/colony/requestsystem/manager/IRequestManager;Lcom/minecolonies/api/colony/requestsystem/request/RequestState;)V
     143: return

  public void removeRequestFromResolver(com.minecolonies.api.colony.requestsystem.resolver.IRequestResolver<?>, com.minecolonies.api.colony.requestsystem.request.IRequest<?>);
    Code:
       0: aload_0
       1: getfield      #16                 // Field manager:Lcom/minecolonies/core/colony/requestsystem/management/IStandardRequestManager;
       4: invokeinterface #135,  1          // InterfaceMethod com/minecolonies/core/colony/requestsystem/management/IStandardRequestManager.getRequestResolverRequestAssignmentDataStore:()Lcom/minecolonies/api/colony/requestsystem/data/IRequestResolverRequestAssignmentDataStore;
       9: invokeinterface #139,  1          // InterfaceMethod com/minecolonies/api/colony/requestsystem/data/IRequestResolverRequestAssignmentDataStore.getAssignments:()Ljava/util/Map;
      14: aload_1
      15: invokeinterface #60,  1           // InterfaceMethod com/minecolonies/api/colony/requestsystem/resolver/IRequestResolver.getId:()Lcom/minecolonies/api/colony/requestsystem/token/IToken;
      20: invokeinterface #145,  2          // InterfaceMethod java/util/Map.containsKey:(Ljava/lang/Object;)Z
      25: ifne          39
      28: new           #72                 // class java/lang/IllegalArgumentException
      31: dup
      32: ldc_w         #309                // String The given resolver is unknown to this Manager
      35: invokespecial #76                 // Method java/lang/IllegalArgumentException."<init>":(Ljava/lang/String;)V
      38: athrow
      39: aload_0
      40: getfield      #16                 // Field manager:Lcom/minecolonies/core/colony/requestsystem/management/IStandardRequestManager;
      43: invokeinterface #135,  1          // InterfaceMethod com/minecolonies/core/colony/requestsystem/management/IStandardRequestManager.getRequestResolverRequestAssignmentDataStore:()Lcom/minecolonies/api/colony/requestsystem/data/IRequestResolverRequestAssignmentDataStore;
      48: invokeinterface #139,  1          // InterfaceMethod com/minecolonies/api/colony/requestsystem/data/IRequestResolverRequestAssignmentDataStore.getAssignments:()Ljava/util/Map;
      53: aload_1
      54: invokeinterface #60,  1           // InterfaceMethod com/minecolonies/api/colony/requestsystem/resolver/IRequestResolver.getId:()Lcom/minecolonies/api/colony/requestsystem/token/IToken;
      59: invokeinterface #148,  2          // InterfaceMethod java/util/Map.get:(Ljava/lang/Object;)Ljava/lang/Object;
      64: checkcast     #46                 // class java/util/Collection
      67: aload_2
      68: invokeinterface #290,  1          // InterfaceMethod com/minecolonies/api/colony/requestsystem/request/IRequest.getId:()Lcom/minecolonies/api/colony/requestsystem/token/IToken;
      73: invokeinterface #161,  2          // InterfaceMethod java/util/Collection.contains:(Ljava/lang/Object;)Z
      78: ifne          92
      81: new           #72                 // class java/lang/IllegalArgumentException
      84: dup
      85: ldc_w         #311                // String The given request is not registered to the given resolver.
      88: invokespecial #76                 // Method java/lang/IllegalArgumentException."<init>":(Ljava/lang/String;)V
      91: athrow
      92: aload_0
      93: getfield      #16                 // Field manager:Lcom/minecolonies/core/colony/requestsystem/management/IStandardRequestManager;
      96: aload_2
      97: invokestatic  #178                // Method java/lang/String.valueOf:(Ljava/lang/Object;)Ljava/lang/String;
     100: aload_1
     101: invokestatic  #178                // Method java/lang/String.valueOf:(Ljava/lang/Object;)Ljava/lang/String;
     104: invokedynamic #313,  0            // InvokeDynamic #8:makeConcatWithConstants:(Ljava/lang/String;Ljava/lang/String;)Ljava/lang/String;
     109: invokeinterface #188,  2          // InterfaceMethod com/minecolonies/core/colony/requestsystem/management/IStandardRequestManager.log:(Ljava/lang/String;)V
     114: aload_0
     115: getfield      #16                 // Field manager:Lcom/minecolonies/core/colony/requestsystem/management/IStandardRequestManager;
     118: invokeinterface #135,  1          // InterfaceMethod com/minecolonies/core/colony/requestsystem/management/IStandardRequestManager.getRequestResolverRequestAssignmentDataStore:()Lcom/minecolonies/api/colony/requestsystem/data/IRequestResolverRequestAssignmentDataStore;
     123: invokeinterface #139,  1          // InterfaceMethod com/minecolonies/api/colony/requestsystem/data/IRequestResolverRequestAssignmentDataStore.getAssignments:()Ljava/util/Map;
     128: aload_1
     129: invokeinterface #60,  1           // InterfaceMethod com/minecolonies/api/colony/requestsystem/resolver/IRequestResolver.getId:()Lcom/minecolonies/api/colony/requestsystem/token/IToken;
     134: invokeinterface #148,  2          // InterfaceMethod java/util/Map.get:(Ljava/lang/Object;)Ljava/lang/Object;
     139: checkcast     #46                 // class java/util/Collection
     142: aload_2
     143: invokeinterface #290,  1          // InterfaceMethod com/minecolonies/api/colony/requestsystem/request/IRequest.getId:()Lcom/minecolonies/api/colony/requestsystem/token/IToken;
     148: invokeinterface #314,  2          // InterfaceMethod java/util/Collection.remove:(Ljava/lang/Object;)Z
     153: pop
     154: aload_0
     155: getfield      #16                 // Field manager:Lcom/minecolonies/core/colony/requestsystem/management/IStandardRequestManager;
     158: invokeinterface #135,  1          // InterfaceMethod com/minecolonies/core/colony/requestsystem/management/IStandardRequestManager.getRequestResolverRequestAssignmentDataStore:()Lcom/minecolonies/api/colony/requestsystem/data/IRequestResolverRequestAssignmentDataStore;
     163: invokeinterface #139,  1          // InterfaceMethod com/minecolonies/api/colony/requestsystem/data/IRequestResolverRequestAssignmentDataStore.getAssignments:()Ljava/util/Map;
     168: aload_1
     169: invokeinterface #60,  1           // InterfaceMethod com/minecolonies/api/colony/requestsystem/resolver/IRequestResolver.getId:()Lcom/minecolonies/api/colony/requestsystem/token/IToken;
     174: invokeinterface #148,  2          // InterfaceMethod java/util/Map.get:(Ljava/lang/Object;)Ljava/lang/Object;
     179: checkcast     #46                 // class java/util/Collection
     182: invokeinterface #152,  1          // InterfaceMethod java/util/Collection.isEmpty:()Z
     187: ifeq          216
     190: aload_0
     191: getfield      #16                 // Field manager:Lcom/minecolonies/core/colony/requestsystem/management/IStandardRequestManager;
     194: invokeinterface #135,  1          // InterfaceMethod com/minecolonies/core/colony/requestsystem/management/IStandardRequestManager.getRequestResolverRequestAssignmentDataStore:()Lcom/minecolonies/api/colony/requestsystem/data/IRequestResolverRequestAssignmentDataStore;
     199: invokeinterface #139,  1          // InterfaceMethod com/minecolonies/api/colony/requestsystem/data/IRequestResolverRequestAssignmentDataStore.getAssignments:()Ljava/util/Map;
     204: aload_1
     205: invokeinterface #60,  1           // InterfaceMethod com/minecolonies/api/colony/requestsystem/resolver/IRequestResolver.getId:()Lcom/minecolonies/api/colony/requestsystem/token/IToken;
     210: invokeinterface #191,  2          // InterfaceMethod java/util/Map.remove:(Ljava/lang/Object;)Ljava/lang/Object;
     215: pop
     216: return

  public com.minecolonies.api.colony.requestsystem.resolver.IRequestResolver<? extends com.minecolonies.api.colony.requestsystem.requestable.IRequestable> getResolverForRequest(com.minecolonies.api.colony.requestsystem.token.IToken<?>);
    Code:
       0: aload_0
       1: getfield      #16                 // Field manager:Lcom/minecolonies/core/colony/requestsystem/management/IStandardRequestManager;
       4: invokeinterface #241,  1          // InterfaceMethod com/minecolonies/core/colony/requestsystem/management/IStandardRequestManager.getRequestHandler:()Lcom/minecolonies/api/colony/requestsystem/management/IRequestHandler;
       9: aload_1
      10: invokeinterface #315,  2          // InterfaceMethod com/minecolonies/api/colony/requestsystem/management/IRequestHandler.getRequest:(Lcom/minecolonies/api/colony/requestsystem/token/IToken;)Lcom/minecolonies/api/colony/requestsystem/request/IRequest;
      15: pop
      16: aload_0
      17: getfield      #16                 // Field manager:Lcom/minecolonies/core/colony/requestsystem/management/IStandardRequestManager;
      20: invokeinterface #135,  1          // InterfaceMethod com/minecolonies/core/colony/requestsystem/management/IStandardRequestManager.getRequestResolverRequestAssignmentDataStore:()Lcom/minecolonies/api/colony/requestsystem/data/IRequestResolverRequestAssignmentDataStore;
      25: aload_1
      26: invokeinterface #318,  2          // InterfaceMethod com/minecolonies/api/colony/requestsystem/data/IRequestResolverRequestAssignmentDataStore.getAssignmentForValue:(Ljava/lang/Object;)Ljava/lang/Object;
      31: checkcast     #224                // class com/minecolonies/api/colony/requestsystem/token/IToken
      34: astore_2
      35: aload_2
      36: ifnonnull     56
      39: new           #72                 // class java/lang/IllegalArgumentException
      42: dup
      43: aload_1
      44: invokestatic  #178                // Method java/lang/String.valueOf:(Ljava/lang/Object;)Ljava/lang/String;
      47: invokedynamic #321,  0            // InvokeDynamic #9:makeConcatWithConstants:(Ljava/lang/String;)Ljava/lang/String;
      52: invokespecial #76                 // Method java/lang/IllegalArgumentException."<init>":(Ljava/lang/String;)V
      55: athrow
      56: aload_0
      57: getfield      #16                 // Field manager:Lcom/minecolonies/core/colony/requestsystem/management/IStandardRequestManager;
      60: invokeinterface #48,  1           // InterfaceMethod com/minecolonies/core/colony/requestsystem/management/IStandardRequestManager.getRequestResolverIdentitiesDataStore:()Lcom/minecolonies/api/colony/requestsystem/data/IRequestResolverIdentitiesDataStore;
      65: invokeinterface #54,  1           // InterfaceMethod com/minecolonies/api/colony/requestsystem/data/IRequestResolverIdentitiesDataStore.getIdentities:()Lcom/google/common/collect/BiMap;
      70: aload_2
      71: invokeinterface #266,  2          // InterfaceMethod com/google/common/collect/BiMap.get:(Ljava/lang/Object;)Ljava/lang/Object;
      76: checkcast     #61                 // class com/minecolonies/api/colony/requestsystem/resolver/IRequestResolver
      79: areturn

  public com.minecolonies.api.colony.requestsystem.resolver.IRequestResolver<? extends com.minecolonies.api.colony.requestsystem.requestable.IRequestable> getResolverForRequest(com.minecolonies.api.colony.requestsystem.request.IRequest<?>);
    Code:
       0: aload_0
       1: aload_1
       2: invokeinterface #290,  1          // InterfaceMethod com/minecolonies/api/colony/requestsystem/request/IRequest.getId:()Lcom/minecolonies/api/colony/requestsystem/token/IToken;
       7: invokevirtual #322                // Method getResolverForRequest:(Lcom/minecolonies/api/colony/requestsystem/token/IToken;)Lcom/minecolonies/api/colony/requestsystem/resolver/IRequestResolver;
      10: areturn

  public void onColonyUpdate(java.util.function.Predicate<com.minecolonies.api.colony.requestsystem.request.IRequest<?>>);
    Code:
       0: aload_0
       1: getfield      #16                 // Field manager:Lcom/minecolonies/core/colony/requestsystem/management/IStandardRequestManager;
       4: invokeinterface #48,  1           // InterfaceMethod com/minecolonies/core/colony/requestsystem/management/IStandardRequestManager.getRequestResolverIdentitiesDataStore:()Lcom/minecolonies/api/colony/requestsystem/data/IRequestResolverIdentitiesDataStore;
       9: invokeinterface #54,  1           // InterfaceMethod com/minecolonies/api/colony/requestsystem/data/IRequestResolverIdentitiesDataStore.getIdentities:()Lcom/google/common/collect/BiMap;
      14: invokeinterface #325,  1          // InterfaceMethod com/google/common/collect/BiMap.values:()Ljava/util/Set;
      19: aload_0
      20: aload_1
      21: invokedynamic #329,  0            // InvokeDynamic #10:accept:(Lcom/minecolonies/core/colony/requestsystem/management/handlers/ResolverHandler;Ljava/util/function/Predicate;)Ljava/util/function/Consumer;
      26: invokeinterface #113,  2          // InterfaceMethod java/util/Set.forEach:(Ljava/util/function/Consumer;)V
      31: return

  public boolean isBeingRemoved(com.minecolonies.api.colony.requestsystem.token.IToken<?>);
    Code:
       0: aload_0
       1: getfield      #10                 // Field tempBlackList:Ljava/util/List;
       4: aload_1
       5: invokeinterface #332,  2          // InterfaceMethod java/util/List.contains:(Ljava/lang/Object;)Z
      10: ireturn
}
