Compiled from "RequestHandler.java"
public class com.minecolonies.core.colony.requestsystem.management.handlers.RequestHandler implements com.minecolonies.api.colony.requestsystem.management.IRequestHandler {
  public com.minecolonies.core.colony.requestsystem.management.handlers.RequestHandler(com.minecolonies.core.colony.requestsystem.management.IStandardRequestManager);
    Code:
       0: aload_0
       1: invokespecial #1                  // Method java/lang/Object."<init>":()V
       4: aload_0
       5: aload_1
       6: putfield      #7                  // Field manager:Lcom/minecolonies/core/colony/requestsystem/management/IStandardRequestManager;
       9: return

  public com.minecolonies.api.colony.requestsystem.manager.IRequestManager getManager();
    Code:
       0: aload_0
       1: getfield      #7                  // Field manager:Lcom/minecolonies/core/colony/requestsystem/management/IStandardRequestManager;
       4: areturn

  public <Request extends com.minecolonies.api.colony.requestsystem.requestable.IRequestable> com.minecolonies.api.colony.requestsystem.request.IRequest<Request> createRequest(com.minecolonies.api.colony.requestsystem.requester.IRequester, Request);
    Code:
       0: aload_0
       1: getfield      #7                  // Field manager:Lcom/minecolonies/core/colony/requestsystem/management/IStandardRequestManager;
       4: invokeinterface #13,  1           // InterfaceMethod com/minecolonies/core/colony/requestsystem/management/IStandardRequestManager.getTokenHandler:()Lcom/minecolonies/api/colony/requestsystem/management/ITokenHandler;
       9: invokeinterface #19,  1           // InterfaceMethod com/minecolonies/api/colony/requestsystem/management/ITokenHandler.generateNewToken:()Lcom/minecolonies/api/colony/requestsystem/token/IToken;
      14: astore_3
      15: aload_0
      16: getfield      #7                  // Field manager:Lcom/minecolonies/core/colony/requestsystem/management/IStandardRequestManager;
      19: invokeinterface #25,  1           // InterfaceMethod com/minecolonies/core/colony/requestsystem/management/IStandardRequestManager.getFactoryController:()Lcom/minecolonies/api/colony/requestsystem/factory/IFactoryController;
      24: invokestatic  #29                 // Method com/minecolonies/api/colony/requestsystem/manager/RequestMappingHandler.getRequestableMappings:()Lcom/google/common/collect/BiMap;
      27: aload_2
      28: invokeinterface #35,  1           // InterfaceMethod com/minecolonies/api/colony/requestsystem/requestable/IRequestable.getClass:()Ljava/lang/Class;
      33: invokeinterface #41,  2           // InterfaceMethod com/google/common/collect/BiMap.get:(Ljava/lang/Object;)Ljava/lang/Object;
      38: checkcast     #47                 // class java/lang/Class
      41: invokestatic  #49                 // Method com/google/common/reflect/TypeToken.of:(Ljava/lang/Class;)Lcom/google/common/reflect/TypeToken;
      44: aload_2
      45: iconst_2
      46: anewarray     #2                  // class java/lang/Object
      49: dup
      50: iconst_0
      51: aload_3
      52: aastore
      53: dup
      54: iconst_1
      55: aload_1
      56: aastore
      57: invokeinterface #55,  4           // InterfaceMethod com/minecolonies/api/colony/requestsystem/factory/IFactoryController.getNewInstance:(Lcom/google/common/reflect/TypeToken;Ljava/lang/Object;[Ljava/lang/Object;)Ljava/lang/Object;
      62: checkcast     #61                 // class com/minecolonies/api/colony/requestsystem/request/IRequest
      65: astore        4
      67: aload_0
      68: getfield      #7                  // Field manager:Lcom/minecolonies/core/colony/requestsystem/management/IStandardRequestManager;
      71: aload_2
      72: invokestatic  #63                 // Method java/lang/String.valueOf:(Ljava/lang/Object;)Ljava/lang/String;
      75: aload_3
      76: invokestatic  #63                 // Method java/lang/String.valueOf:(Ljava/lang/Object;)Ljava/lang/String;
      79: aload         4
      81: invokestatic  #63                 // Method java/lang/String.valueOf:(Ljava/lang/Object;)Ljava/lang/String;
      84: invokedynamic #69,  0             // InvokeDynamic #0:makeConcatWithConstants:(Ljava/lang/String;Ljava/lang/String;Ljava/lang/String;)Ljava/lang/String;
      89: invokeinterface #73,  2           // InterfaceMethod com/minecolonies/core/colony/requestsystem/management/IStandardRequestManager.log:(Ljava/lang/String;)V
      94: aload_0
      95: aload         4
      97: invokevirtual #77                 // Method registerRequest:(Lcom/minecolonies/api/colony/requestsystem/request/IRequest;)V
     100: aload         4
     102: areturn

  public void registerRequest(com.minecolonies.api.colony.requestsystem.request.IRequest<?>);
    Code:
       0: aload_0
       1: getfield      #7                  // Field manager:Lcom/minecolonies/core/colony/requestsystem/management/IStandardRequestManager;
       4: invokeinterface #81,  1           // InterfaceMethod com/minecolonies/core/colony/requestsystem/management/IStandardRequestManager.getRequestIdentitiesDataStore:()Lcom/minecolonies/api/colony/requestsystem/data/IRequestIdentitiesDataStore;
       9: invokeinterface #85,  1           // InterfaceMethod com/minecolonies/api/colony/requestsystem/data/IRequestIdentitiesDataStore.getIdentities:()Lcom/google/common/collect/BiMap;
      14: aload_1
      15: invokeinterface #90,  1           // InterfaceMethod com/minecolonies/api/colony/requestsystem/request/IRequest.getId:()Lcom/minecolonies/api/colony/requestsystem/token/IToken;
      20: invokeinterface #93,  2           // InterfaceMethod com/google/common/collect/BiMap.containsKey:(Ljava/lang/Object;)Z
      25: ifne          51
      28: aload_0
      29: getfield      #7                  // Field manager:Lcom/minecolonies/core/colony/requestsystem/management/IStandardRequestManager;
      32: invokeinterface #81,  1           // InterfaceMethod com/minecolonies/core/colony/requestsystem/management/IStandardRequestManager.getRequestIdentitiesDataStore:()Lcom/minecolonies/api/colony/requestsystem/data/IRequestIdentitiesDataStore;
      37: invokeinterface #85,  1           // InterfaceMethod com/minecolonies/api/colony/requestsystem/data/IRequestIdentitiesDataStore.getIdentities:()Lcom/google/common/collect/BiMap;
      42: aload_1
      43: invokeinterface #97,  2           // InterfaceMethod com/google/common/collect/BiMap.containsValue:(Ljava/lang/Object;)Z
      48: ifeq          61
      51: new           #100                // class java/lang/IllegalArgumentException
      54: dup
      55: ldc           #102                // String The given request is already known to this manager
      57: invokespecial #104                // Method java/lang/IllegalArgumentException."<init>":(Ljava/lang/String;)V
      60: athrow
      61: aload_0
      62: getfield      #7                  // Field manager:Lcom/minecolonies/core/colony/requestsystem/management/IStandardRequestManager;
      65: aload_1
      66: invokestatic  #63                 // Method java/lang/String.valueOf:(Ljava/lang/Object;)Ljava/lang/String;
      69: invokedynamic #106,  0            // InvokeDynamic #1:makeConcatWithConstants:(Ljava/lang/String;)Ljava/lang/String;
      74: invokeinterface #73,  2           // InterfaceMethod com/minecolonies/core/colony/requestsystem/management/IStandardRequestManager.log:(Ljava/lang/String;)V
      79: aload_0
      80: getfield      #7                  // Field manager:Lcom/minecolonies/core/colony/requestsystem/management/IStandardRequestManager;
      83: invokeinterface #81,  1           // InterfaceMethod com/minecolonies/core/colony/requestsystem/management/IStandardRequestManager.getRequestIdentitiesDataStore:()Lcom/minecolonies/api/colony/requestsystem/data/IRequestIdentitiesDataStore;
      88: invokeinterface #85,  1           // InterfaceMethod com/minecolonies/api/colony/requestsystem/data/IRequestIdentitiesDataStore.getIdentities:()Lcom/google/common/collect/BiMap;
      93: aload_1
      94: invokeinterface #90,  1           // InterfaceMethod com/minecolonies/api/colony/requestsystem/request/IRequest.getId:()Lcom/minecolonies/api/colony/requestsystem/token/IToken;
      99: aload_1
     100: invokeinterface #109,  3          // InterfaceMethod com/google/common/collect/BiMap.put:(Ljava/lang/Object;Ljava/lang/Object;)Ljava/lang/Object;
     105: pop
     106: return

  public void assignRequest(com.minecolonies.api.colony.requestsystem.request.IRequest<?>);
    Code:
       0: aload_0
       1: aload_1
       2: invokestatic  #113                // Method java/util/Collections.emptyList:()Ljava/util/List;
       5: invokevirtual #119                // Method assignRequest:(Lcom/minecolonies/api/colony/requestsystem/request/IRequest;Ljava/util/Collection;)Lcom/minecolonies/api/colony/requestsystem/token/IToken;
       8: pop
       9: return

  public com.minecolonies.api.colony.requestsystem.token.IToken<?> assignRequest(com.minecolonies.api.colony.requestsystem.request.IRequest<?>, java.util.Collection<com.minecolonies.api.colony.requestsystem.token.IToken<?>>);
    Code:
       0: getstatic     #123                // Field com/minecolonies/core/colony/requestsystem/management/handlers/RequestHandler$1.$SwitchMap$com$minecolonies$api$colony$requestsystem$manager$AssigningStrategy:[I
       3: aload_1
       4: invokeinterface #129,  1          // InterfaceMethod com/minecolonies/api/colony/requestsystem/request/IRequest.getStrategy:()Lcom/minecolonies/api/colony/requestsystem/manager/AssigningStrategy;
       9: invokevirtual #133                // Method com/minecolonies/api/colony/requestsystem/manager/AssigningStrategy.ordinal:()I
      12: iaload
      13: lookupswitch  { // 2

                     1: 40

                     2: 47
               default: 64
          }
      40: aload_0
      41: aload_1
      42: aload_2
      43: invokevirtual #139                // Method assignRequestDefault:(Lcom/minecolonies/api/colony/requestsystem/request/IRequest;Ljava/util/Collection;)Lcom/minecolonies/api/colony/requestsystem/token/IToken;
      46: areturn
      47: invokestatic  #142                // Method com/minecolonies/api/util/Log.getLogger:()Lorg/apache/logging/log4j/Logger;
      50: ldc           #148                // String Fastest First strategy not implemented yet.
      52: invokeinterface #150,  2          // InterfaceMethod org/apache/logging/log4j/Logger.warn:(Ljava/lang/String;)V
      57: aload_0
      58: aload_1
      59: aload_2
      60: invokevirtual #139                // Method assignRequestDefault:(Lcom/minecolonies/api/colony/requestsystem/request/IRequest;Ljava/util/Collection;)Lcom/minecolonies/api/colony/requestsystem/token/IToken;
      63: areturn
      64: aconst_null
      65: areturn

  public com.minecolonies.api.colony.requestsystem.token.IToken<?> assignRequestDefault(com.minecolonies.api.colony.requestsystem.request.IRequest<?>, java.util.Collection<com.minecolonies.api.colony.requestsystem.token.IToken<?>>);
    Code:
       0: aload_0
       1: aload_1
       2: invokeinterface #90,  1           // InterfaceMethod com/minecolonies/api/colony/requestsystem/request/IRequest.getId:()Lcom/minecolonies/api/colony/requestsystem/token/IToken;
       7: invokevirtual #155                // Method getRequest:(Lcom/minecolonies/api/colony/requestsystem/token/IToken;)Lcom/minecolonies/api/colony/requestsystem/request/IRequest;
      10: pop
      11: aload_0
      12: getfield      #7                  // Field manager:Lcom/minecolonies/core/colony/requestsystem/management/IStandardRequestManager;
      15: aload_1
      16: invokestatic  #63                 // Method java/lang/String.valueOf:(Ljava/lang/Object;)Ljava/lang/String;
      19: invokedynamic #159,  0            // InvokeDynamic #2:makeConcatWithConstants:(Ljava/lang/String;)Ljava/lang/String;
      24: invokeinterface #73,  2           // InterfaceMethod com/minecolonies/core/colony/requestsystem/management/IStandardRequestManager.log:(Ljava/lang/String;)V
      29: aload_1
      30: new           #160                // class com/minecolonies/core/colony/requestsystem/management/manager/wrapped/WrappedStaticStateRequestManager
      33: dup
      34: aload_0
      35: getfield      #7                  // Field manager:Lcom/minecolonies/core/colony/requestsystem/management/IStandardRequestManager;
      38: invokespecial #162                // Method com/minecolonies/core/colony/requestsystem/management/manager/wrapped/WrappedStaticStateRequestManager."<init>":(Lcom/minecolonies/core/colony/requestsystem/management/IStandardRequestManager;)V
      41: getstatic     #165                // Field com/minecolonies/api/colony/requestsystem/request/RequestState.ASSIGNING:Lcom/minecolonies/api/colony/requestsystem/request/RequestState;
      44: invokeinterface #171,  3          // InterfaceMethod com/minecolonies/api/colony/requestsystem/request/IRequest.setState:(Lcom/minecolonies/api/colony/requestsystem/manager/IRequestManager;Lcom/minecolonies/api/colony/requestsystem/request/RequestState;)V
      49: aload_1
      50: invokeinterface #175,  1          // InterfaceMethod com/minecolonies/api/colony/requestsystem/request/IRequest.getSuperClasses:()Ljava/util/Set;
      55: astore_3
      56: new           #179                // class java/util/LinkedList
      59: dup
      60: aload_3
      61: invokespecial #181                // Method java/util/LinkedList."<init>":(Ljava/util/Collection;)V
      64: astore        4
      66: new           #184                // class java/util/ArrayList
      69: dup
      70: invokespecial #186                // Method java/util/ArrayList."<init>":()V
      73: astore        5
      75: aload_3
      76: invokeinterface #187,  1          // InterfaceMethod java/util/Set.iterator:()Ljava/util/Iterator;
      81: astore        6
      83: aload         6
      85: invokeinterface #193,  1          // InterfaceMethod java/util/Iterator.hasNext:()Z
      90: ifeq          220
      93: aload         6
      95: invokeinterface #199,  1          // InterfaceMethod java/util/Iterator.next:()Ljava/lang/Object;
     100: checkcast     #50                 // class com/google/common/reflect/TypeToken
     103: astore        7
     105: aload_0
     106: getfield      #7                  // Field manager:Lcom/minecolonies/core/colony/requestsystem/management/IStandardRequestManager;
     109: invokeinterface #203,  1          // InterfaceMethod com/minecolonies/core/colony/requestsystem/management/IStandardRequestManager.getRequestableTypeRequestResolverAssignmentDataStore:()Lcom/minecolonies/api/colony/requestsystem/data/IRequestableTypeRequestResolverAssignmentDataStore;
     114: invokeinterface #207,  1          // InterfaceMethod com/minecolonies/api/colony/requestsystem/data/IRequestableTypeRequestResolverAssignmentDataStore.getAssignments:()Ljava/util/Map;
     119: aload         7
     121: invokeinterface #213,  2          // InterfaceMethod java/util/Map.get:(Ljava/lang/Object;)Ljava/lang/Object;
     126: checkcast     #216                // class java/util/Collection
     129: astore        8
     131: aload         8
     133: ifnonnull     139
     136: goto          83
     139: aload         8
     141: invokeinterface #218,  1          // InterfaceMethod java/util/Collection.iterator:()Ljava/util/Iterator;
     146: astore        9
     148: aload         9
     150: invokeinterface #193,  1          // InterfaceMethod java/util/Iterator.hasNext:()Z
     155: ifeq          217
     158: aload         9
     160: invokeinterface #199,  1          // InterfaceMethod java/util/Iterator.next:()Ljava/lang/Object;
     165: checkcast     #219                // class com/minecolonies/api/colony/requestsystem/token/IToken
     168: astore        10
     170: aload_0
     171: getfield      #7                  // Field manager:Lcom/minecolonies/core/colony/requestsystem/management/IStandardRequestManager;
     174: invokeinterface #221,  1          // InterfaceMethod com/minecolonies/core/colony/requestsystem/management/IStandardRequestManager.getResolverHandler:()Lcom/minecolonies/api/colony/requestsystem/management/IResolverHandler;
     179: aload         10
     181: invokeinterface #225,  2          // InterfaceMethod com/minecolonies/api/colony/requestsystem/management/IResolverHandler.getResolver:(Lcom/minecolonies/api/colony/requestsystem/token/IToken;)Lcom/minecolonies/api/colony/requestsystem/resolver/IRequestResolver;
     186: astore        11
     188: aload_3
     189: aload         11
     191: invokeinterface #231,  1          // InterfaceMethod com/minecolonies/api/colony/requestsystem/resolver/IRequestResolver.getRequestType:()Lcom/google/common/reflect/TypeToken;
     196: invokeinterface #237,  2          // InterfaceMethod java/util/Set.contains:(Ljava/lang/Object;)Z
     201: ifeq          214
     204: aload         5
     206: aload         11
     208: invokeinterface #240,  2          // InterfaceMethod java/util/List.add:(Ljava/lang/Object;)Z
     213: pop
     214: goto          148
     217: goto          83
     220: aload         5
     222: invokedynamic #245,  0            // InvokeDynamic #3:applyAsInt:()Ljava/util/function/ToIntFunction;
     227: invokestatic  #249                // InterfaceMethod java/util/Comparator.comparingInt:(Ljava/util/function/ToIntFunction;)Ljava/util/Comparator;
     230: aload         4
     232: invokedynamic #255,  0            // InvokeDynamic #4:applyAsInt:(Ljava/util/List;)Ljava/util/function/ToIntFunction;
     237: invokeinterface #258,  2          // InterfaceMethod java/util/Comparator.thenComparingInt:(Ljava/util/function/ToIntFunction;)Ljava/util/Comparator;
     242: invokeinterface #261,  2          // InterfaceMethod java/util/List.sort:(Ljava/util/Comparator;)V
     247: new           #265                // class java/util/LinkedHashSet
     250: dup
     251: aload         5
     253: invokespecial #267                // Method java/util/LinkedHashSet."<init>":(Ljava/util/Collection;)V
     256: astore        6
     258: aconst_null
     259: astore        7
     261: ldc_w         #270                // int 2147483647
     264: istore        8
     266: aconst_null
     267: astore        9
     269: aload         6
     271: invokeinterface #187,  1          // InterfaceMethod java/util/Set.iterator:()Ljava/util/Iterator;
     276: astore        10
     278: aload         10
     280: invokeinterface #193,  1          // InterfaceMethod java/util/Iterator.hasNext:()Z
     285: ifeq          512
     288: aload         10
     290: invokeinterface #199,  1          // InterfaceMethod java/util/Iterator.next:()Ljava/lang/Object;
     295: checkcast     #232                // class com/minecolonies/api/colony/requestsystem/resolver/IRequestResolver
     298: astore        11
     300: aload_2
     301: aload         11
     303: invokeinterface #271,  1          // InterfaceMethod com/minecolonies/api/colony/requestsystem/resolver/IRequestResolver.getId:()Lcom/minecolonies/api/colony/requestsystem/token/IToken;
     308: invokeinterface #272,  2          // InterfaceMethod java/util/Collection.contains:(Ljava/lang/Object;)Z
     313: ifne          278
     316: aload_0
     317: getfield      #7                  // Field manager:Lcom/minecolonies/core/colony/requestsystem/management/IStandardRequestManager;
     320: invokeinterface #221,  1          // InterfaceMethod com/minecolonies/core/colony/requestsystem/management/IStandardRequestManager.getResolverHandler:()Lcom/minecolonies/api/colony/requestsystem/management/IResolverHandler;
     325: aload         11
     327: invokeinterface #271,  1          // InterfaceMethod com/minecolonies/api/colony/requestsystem/resolver/IRequestResolver.getId:()Lcom/minecolonies/api/colony/requestsystem/token/IToken;
     332: invokeinterface #273,  2          // InterfaceMethod com/minecolonies/api/colony/requestsystem/management/IResolverHandler.isBeingRemoved:(Lcom/minecolonies/api/colony/requestsystem/token/IToken;)Z
     337: ifeq          343
     340: goto          278
     343: aload         7
     345: ifnull        368
     348: aload         7
     350: invokeinterface #277,  1          // InterfaceMethod com/minecolonies/api/colony/requestsystem/resolver/IRequestResolver.getPriority:()I
     355: aload         11
     357: invokeinterface #277,  1          // InterfaceMethod com/minecolonies/api/colony/requestsystem/resolver/IRequestResolver.getPriority:()I
     362: if_icmpeq     368
     365: goto          512
     368: aload         11
     370: aload_0
     371: getfield      #7                  // Field manager:Lcom/minecolonies/core/colony/requestsystem/management/IStandardRequestManager;
     374: aload_1
     375: invokeinterface #280,  3          // InterfaceMethod com/minecolonies/api/colony/requestsystem/resolver/IRequestResolver.canResolveRequest:(Lcom/minecolonies/api/colony/requestsystem/manager/IRequestManager;Lcom/minecolonies/api/colony/requestsystem/request/IRequest;)Z
     380: ifne          386
     383: goto          278
     386: aload         7
     388: ifnonnull     439
     391: aload         11
     393: new           #284                // class com/minecolonies/core/colony/requestsystem/management/manager/wrapped/WrappedBlacklistAssignmentRequestManager
     396: dup
     397: aload_0
     398: getfield      #7                  // Field manager:Lcom/minecolonies/core/colony/requestsystem/management/IStandardRequestManager;
     401: aload_2
     402: invokespecial #286                // Method com/minecolonies/core/colony/requestsystem/management/manager/wrapped/WrappedBlacklistAssignmentRequestManager."<init>":(Lcom/minecolonies/core/colony/requestsystem/management/IStandardRequestManager;Ljava/util/Collection;)V
     405: aload_1
     406: invokeinterface #289,  3          // InterfaceMethod com/minecolonies/api/colony/requestsystem/resolver/IRequestResolver.attemptResolveRequest:(Lcom/minecolonies/api/colony/requestsystem/manager/IRequestManager;Lcom/minecolonies/api/colony/requestsystem/request/IRequest;)Ljava/util/List;
     411: astore        9
     413: aload         9
     415: ifnull        509
     418: aload         11
     420: astore        7
     422: aload         11
     424: aload_0
     425: getfield      #7                  // Field manager:Lcom/minecolonies/core/colony/requestsystem/management/IStandardRequestManager;
     428: aload_1
     429: invokeinterface #293,  3          // InterfaceMethod com/minecolonies/api/colony/requestsystem/resolver/IRequestResolver.getSuitabilityMetric:(Lcom/minecolonies/api/colony/requestsystem/manager/IRequestManager;Lcom/minecolonies/api/colony/requestsystem/request/IRequest;)I
     434: istore        8
     436: goto          509
     439: aload         11
     441: aload_0
     442: getfield      #7                  // Field manager:Lcom/minecolonies/core/colony/requestsystem/management/IStandardRequestManager;
     445: aload_1
     446: invokeinterface #293,  3          // InterfaceMethod com/minecolonies/api/colony/requestsystem/resolver/IRequestResolver.getSuitabilityMetric:(Lcom/minecolonies/api/colony/requestsystem/manager/IRequestManager;Lcom/minecolonies/api/colony/requestsystem/request/IRequest;)I
     451: istore        12
     453: iload         12
     455: iload         8
     457: if_icmpge     509
     460: aload         11
     462: new           #284                // class com/minecolonies/core/colony/requestsystem/management/manager/wrapped/WrappedBlacklistAssignmentRequestManager
     465: dup
     466: aload_0
     467: getfield      #7                  // Field manager:Lcom/minecolonies/core/colony/requestsystem/management/IStandardRequestManager;
     470: aload_2
     471: invokespecial #286                // Method com/minecolonies/core/colony/requestsystem/management/manager/wrapped/WrappedBlacklistAssignmentRequestManager."<init>":(Lcom/minecolonies/core/colony/requestsystem/management/IStandardRequestManager;Ljava/util/Collection;)V
     474: aload_1
     475: invokeinterface #289,  3          // InterfaceMethod com/minecolonies/api/colony/requestsystem/resolver/IRequestResolver.attemptResolveRequest:(Lcom/minecolonies/api/colony/requestsystem/manager/IRequestManager;Lcom/minecolonies/api/colony/requestsystem/request/IRequest;)Ljava/util/List;
     480: astore        13
     482: aload         13
     484: ifnull        509
     487: aload         11
     489: astore        7
     491: aload         11
     493: aload_0
     494: getfield      #7                  // Field manager:Lcom/minecolonies/core/colony/requestsystem/management/IStandardRequestManager;
     497: aload_1
     498: invokeinterface #293,  3          // InterfaceMethod com/minecolonies/api/colony/requestsystem/resolver/IRequestResolver.getSuitabilityMetric:(Lcom/minecolonies/api/colony/requestsystem/manager/IRequestManager;Lcom/minecolonies/api/colony/requestsystem/request/IRequest;)I
     503: istore        8
     505: aload         13
     507: astore        9
     509: goto          278
     512: aload         7
     514: ifnull        528
     517: aload_0
     518: aload_1
     519: aload         7
     521: aload_2
     522: aload         9
     524: invokevirtual #297                // Method resolve:(Lcom/minecolonies/api/colony/requestsystem/request/IRequest;Lcom/minecolonies/api/colony/requestsystem/resolver/IRequestResolver;Ljava/util/Collection;Ljava/util/List;)Lcom/minecolonies/api/colony/requestsystem/token/IToken;
     527: areturn
     528: aconst_null
     529: areturn

  public com.minecolonies.api.colony.requestsystem.token.IToken<?> reassignRequest(com.minecolonies.api.colony.requestsystem.request.IRequest<?>, java.util.Collection<com.minecolonies.api.colony.requestsystem.token.IToken<?>>);
    Code:
       0: aload_1
       1: invokeinterface #336,  1          // InterfaceMethod com/minecolonies/api/colony/requestsystem/request/IRequest.hasChildren:()Z
       6: ifeq          20
       9: new           #100                // class java/lang/IllegalArgumentException
      12: dup
      13: ldc_w         #342                // String Can not reassign a request that has children.
      16: invokespecial #104                // Method java/lang/IllegalArgumentException."<init>":(Ljava/lang/String;)V
      19: athrow
      20: aload_0
      21: getfield      #7                  // Field manager:Lcom/minecolonies/core/colony/requestsystem/management/IStandardRequestManager;
      24: aload_1
      25: invokeinterface #90,  1           // InterfaceMethod com/minecolonies/api/colony/requestsystem/request/IRequest.getId:()Lcom/minecolonies/api/colony/requestsystem/token/IToken;
      30: invokeinterface #344,  2          // InterfaceMethod com/minecolonies/core/colony/requestsystem/management/IStandardRequestManager.getResolverForRequest:(Lcom/minecolonies/api/colony/requestsystem/token/IToken;)Lcom/minecolonies/api/colony/requestsystem/resolver/IRequestResolver;
      35: astore_3
      36: aload_3
      37: new           #160                // class com/minecolonies/core/colony/requestsystem/management/manager/wrapped/WrappedStaticStateRequestManager
      40: dup
      41: aload_0
      42: getfield      #7                  // Field manager:Lcom/minecolonies/core/colony/requestsystem/management/IStandardRequestManager;
      45: invokespecial #162                // Method com/minecolonies/core/colony/requestsystem/management/manager/wrapped/WrappedStaticStateRequestManager."<init>":(Lcom/minecolonies/core/colony/requestsystem/management/IStandardRequestManager;)V
      48: aload_1
      49: invokeinterface #347,  3          // InterfaceMethod com/minecolonies/api/colony/requestsystem/resolver/IRequestResolver.onAssignedRequestBeingCancelled:(Lcom/minecolonies/api/colony/requestsystem/manager/IRequestManager;Lcom/minecolonies/api/colony/requestsystem/request/IRequest;)V
      54: aload_0
      55: getfield      #7                  // Field manager:Lcom/minecolonies/core/colony/requestsystem/management/IStandardRequestManager;
      58: invokeinterface #351,  1          // InterfaceMethod com/minecolonies/core/colony/requestsystem/management/IStandardRequestManager.getRequestResolverRequestAssignmentDataStore:()Lcom/minecolonies/api/colony/requestsystem/data/IRequestResolverRequestAssignmentDataStore;
      63: invokeinterface #355,  1          // InterfaceMethod com/minecolonies/api/colony/requestsystem/data/IRequestResolverRequestAssignmentDataStore.getAssignments:()Ljava/util/Map;
      68: aload_3
      69: invokeinterface #271,  1          // InterfaceMethod com/minecolonies/api/colony/requestsystem/resolver/IRequestResolver.getId:()Lcom/minecolonies/api/colony/requestsystem/token/IToken;
      74: invokeinterface #358,  2          // InterfaceMethod java/util/Map.containsKey:(Ljava/lang/Object;)Z
      79: ifeq          184
      82: aload_0
      83: getfield      #7                  // Field manager:Lcom/minecolonies/core/colony/requestsystem/management/IStandardRequestManager;
      86: invokeinterface #351,  1          // InterfaceMethod com/minecolonies/core/colony/requestsystem/management/IStandardRequestManager.getRequestResolverRequestAssignmentDataStore:()Lcom/minecolonies/api/colony/requestsystem/data/IRequestResolverRequestAssignmentDataStore;
      91: invokeinterface #355,  1          // InterfaceMethod com/minecolonies/api/colony/requestsystem/data/IRequestResolverRequestAssignmentDataStore.getAssignments:()Ljava/util/Map;
      96: aload_3
      97: invokeinterface #271,  1          // InterfaceMethod com/minecolonies/api/colony/requestsystem/resolver/IRequestResolver.getId:()Lcom/minecolonies/api/colony/requestsystem/token/IToken;
     102: invokeinterface #213,  2          // InterfaceMethod java/util/Map.get:(Ljava/lang/Object;)Ljava/lang/Object;
     107: checkcast     #216                // class java/util/Collection
     110: aload_1
     111: invokeinterface #90,  1           // InterfaceMethod com/minecolonies/api/colony/requestsystem/request/IRequest.getId:()Lcom/minecolonies/api/colony/requestsystem/token/IToken;
     116: invokeinterface #359,  2          // InterfaceMethod java/util/Collection.remove:(Ljava/lang/Object;)Z
     121: pop
     122: aload_0
     123: getfield      #7                  // Field manager:Lcom/minecolonies/core/colony/requestsystem/management/IStandardRequestManager;
     126: invokeinterface #351,  1          // InterfaceMethod com/minecolonies/core/colony/requestsystem/management/IStandardRequestManager.getRequestResolverRequestAssignmentDataStore:()Lcom/minecolonies/api/colony/requestsystem/data/IRequestResolverRequestAssignmentDataStore;
     131: invokeinterface #355,  1          // InterfaceMethod com/minecolonies/api/colony/requestsystem/data/IRequestResolverRequestAssignmentDataStore.getAssignments:()Ljava/util/Map;
     136: aload_3
     137: invokeinterface #271,  1          // InterfaceMethod com/minecolonies/api/colony/requestsystem/resolver/IRequestResolver.getId:()Lcom/minecolonies/api/colony/requestsystem/token/IToken;
     142: invokeinterface #213,  2          // InterfaceMethod java/util/Map.get:(Ljava/lang/Object;)Ljava/lang/Object;
     147: checkcast     #216                // class java/util/Collection
     150: invokeinterface #362,  1          // InterfaceMethod java/util/Collection.isEmpty:()Z
     155: ifeq          184
     158: aload_0
     159: getfield      #7                  // Field manager:Lcom/minecolonies/core/colony/requestsystem/management/IStandardRequestManager;
     162: invokeinterface #351,  1          // InterfaceMethod com/minecolonies/core/colony/requestsystem/management/IStandardRequestManager.getRequestResolverRequestAssignmentDataStore:()Lcom/minecolonies/api/colony/requestsystem/data/IRequestResolverRequestAssignmentDataStore;
     167: invokeinterface #355,  1          // InterfaceMethod com/minecolonies/api/colony/requestsystem/data/IRequestResolverRequestAssignmentDataStore.getAssignments:()Ljava/util/Map;
     172: aload_3
     173: invokeinterface #271,  1          // InterfaceMethod com/minecolonies/api/colony/requestsystem/resolver/IRequestResolver.getId:()Lcom/minecolonies/api/colony/requestsystem/token/IToken;
     178: invokeinterface #365,  2          // InterfaceMethod java/util/Map.remove:(Ljava/lang/Object;)Ljava/lang/Object;
     183: pop
     184: aload_3
     185: new           #160                // class com/minecolonies/core/colony/requestsystem/management/manager/wrapped/WrappedStaticStateRequestManager
     188: dup
     189: aload_0
     190: getfield      #7                  // Field manager:Lcom/minecolonies/core/colony/requestsystem/management/IStandardRequestManager;
     193: invokespecial #162                // Method com/minecolonies/core/colony/requestsystem/management/manager/wrapped/WrappedStaticStateRequestManager."<init>":(Lcom/minecolonies/core/colony/requestsystem/management/IStandardRequestManager;)V
     196: aload_1
     197: invokeinterface #367,  3          // InterfaceMethod com/minecolonies/api/colony/requestsystem/resolver/IRequestResolver.onAssignedRequestCancelled:(Lcom/minecolonies/api/colony/requestsystem/manager/IRequestManager;Lcom/minecolonies/api/colony/requestsystem/request/IRequest;)V
     202: aload_0
     203: getfield      #7                  // Field manager:Lcom/minecolonies/core/colony/requestsystem/management/IStandardRequestManager;
     206: aload_1
     207: invokeinterface #90,  1           // InterfaceMethod com/minecolonies/api/colony/requestsystem/request/IRequest.getId:()Lcom/minecolonies/api/colony/requestsystem/token/IToken;
     212: getstatic     #370                // Field com/minecolonies/api/colony/requestsystem/request/RequestState.REPORTED:Lcom/minecolonies/api/colony/requestsystem/request/RequestState;
     215: invokeinterface #373,  3          // InterfaceMethod com/minecolonies/core/colony/requestsystem/management/IStandardRequestManager.updateRequestState:(Lcom/minecolonies/api/colony/requestsystem/token/IToken;Lcom/minecolonies/api/colony/requestsystem/request/RequestState;)V
     220: aload_0
     221: aload_1
     222: aload_2
     223: invokevirtual #119                // Method assignRequest:(Lcom/minecolonies/api/colony/requestsystem/request/IRequest;Ljava/util/Collection;)Lcom/minecolonies/api/colony/requestsystem/token/IToken;
     226: astore        4
     228: aload         4
     230: areturn

  public boolean isAssigned(com.minecolonies.api.colony.requestsystem.token.IToken<?>);
    Code:
       0: aload_0
       1: getfield      #7                  // Field manager:Lcom/minecolonies/core/colony/requestsystem/management/IStandardRequestManager;
       4: invokeinterface #351,  1          // InterfaceMethod com/minecolonies/core/colony/requestsystem/management/IStandardRequestManager.getRequestResolverRequestAssignmentDataStore:()Lcom/minecolonies/api/colony/requestsystem/data/IRequestResolverRequestAssignmentDataStore;
       9: aload_1
      10: invokeinterface #377,  2          // InterfaceMethod com/minecolonies/api/colony/requestsystem/data/IRequestResolverRequestAssignmentDataStore.getAssignmentForValue:(Ljava/lang/Object;)Ljava/lang/Object;
      15: ifnull        22
      18: iconst_1
      19: goto          23
      22: iconst_0
      23: ireturn

  public void onRequestResolved(com.minecolonies.api.colony.requestsystem.token.IToken<?>);
    Code:
       0: aload_0
       1: aload_1
       2: invokevirtual #155                // Method getRequest:(Lcom/minecolonies/api/colony/requestsystem/token/IToken;)Lcom/minecolonies/api/colony/requestsystem/request/IRequest;
       5: astore_2
       6: aload_0
       7: getfield      #7                  // Field manager:Lcom/minecolonies/core/colony/requestsystem/management/IStandardRequestManager;
      10: invokeinterface #221,  1          // InterfaceMethod com/minecolonies/core/colony/requestsystem/management/IStandardRequestManager.getResolverHandler:()Lcom/minecolonies/api/colony/requestsystem/management/IResolverHandler;
      15: aload_1
      16: invokeinterface #380,  2          // InterfaceMethod com/minecolonies/api/colony/requestsystem/management/IResolverHandler.getResolverForRequest:(Lcom/minecolonies/api/colony/requestsystem/token/IToken;)Lcom/minecolonies/api/colony/requestsystem/resolver/IRequestResolver;
      21: astore_3
      22: aload_3
      23: aload_0
      24: getfield      #7                  // Field manager:Lcom/minecolonies/core/colony/requestsystem/management/IStandardRequestManager;
      27: aload_2
      28: invokeinterface #381,  3          // InterfaceMethod com/minecolonies/api/colony/requestsystem/resolver/IRequestResolver.getFollowupRequestForCompletion:(Lcom/minecolonies/api/colony/requestsystem/manager/IRequestManager;Lcom/minecolonies/api/colony/requestsystem/request/IRequest;)Ljava/util/List;
      33: astore        4
      35: aload_2
      36: aload_0
      37: getfield      #7                  // Field manager:Lcom/minecolonies/core/colony/requestsystem/management/IStandardRequestManager;
      40: getstatic     #384                // Field com/minecolonies/api/colony/requestsystem/request/RequestState.FOLLOWUP_IN_PROGRESS:Lcom/minecolonies/api/colony/requestsystem/request/RequestState;
      43: invokeinterface #171,  3          // InterfaceMethod com/minecolonies/api/colony/requestsystem/request/IRequest.setState:(Lcom/minecolonies/api/colony/requestsystem/manager/IRequestManager;Lcom/minecolonies/api/colony/requestsystem/request/RequestState;)V
      48: aload         4
      50: ifnull        89
      53: aload         4
      55: invokeinterface #387,  1          // InterfaceMethod java/util/List.isEmpty:()Z
      60: ifne          89
      63: aload         4
      65: aload_2
      66: invokedynamic #388,  0            // InvokeDynamic #6:accept:(Lcom/minecolonies/api/colony/requestsystem/request/IRequest;)Ljava/util/function/Consumer;
      71: invokeinterface #392,  2          // InterfaceMethod java/util/List.forEach:(Ljava/util/function/Consumer;)V
      76: aload         4
      78: aload_2
      79: invokedynamic #396,  0            // InvokeDynamic #7:accept:(Lcom/minecolonies/api/colony/requestsystem/request/IRequest;)Ljava/util/function/Consumer;
      84: invokeinterface #392,  2          // InterfaceMethod java/util/List.forEach:(Ljava/util/function/Consumer;)V
      89: aload         4
      91: ifnull        133
      94: aload         4
      96: invokeinterface #387,  1          // InterfaceMethod java/util/List.isEmpty:()Z
     101: ifne          133
     104: aload         4
     106: invokeinterface #397,  1          // InterfaceMethod java/util/List.stream:()Ljava/util/stream/Stream;
     111: aload_0
     112: invokedynamic #401,  0            // InvokeDynamic #8:test:(Lcom/minecolonies/core/colony/requestsystem/management/handlers/RequestHandler;)Ljava/util/function/Predicate;
     117: invokeinterface #405,  2          // InterfaceMethod java/util/stream/Stream.filter:(Ljava/util/function/Predicate;)Ljava/util/stream/Stream;
     122: aload_0
     123: invokedynamic #411,  0            // InvokeDynamic #9:accept:(Lcom/minecolonies/core/colony/requestsystem/management/handlers/RequestHandler;)Ljava/util/function/Consumer;
     128: invokeinterface #414,  2          // InterfaceMethod java/util/stream/Stream.forEach:(Ljava/util/function/Consumer;)V
     133: aload_2
     134: invokeinterface #336,  1          // InterfaceMethod com/minecolonies/api/colony/requestsystem/request/IRequest.hasChildren:()Z
     139: ifne          160
     142: aload_0
     143: getfield      #7                  // Field manager:Lcom/minecolonies/core/colony/requestsystem/management/IStandardRequestManager;
     146: aload_2
     147: invokeinterface #90,  1           // InterfaceMethod com/minecolonies/api/colony/requestsystem/request/IRequest.getId:()Lcom/minecolonies/api/colony/requestsystem/token/IToken;
     152: getstatic     #415                // Field com/minecolonies/api/colony/requestsystem/request/RequestState.COMPLETED:Lcom/minecolonies/api/colony/requestsystem/request/RequestState;
     155: invokeinterface #373,  3          // InterfaceMethod com/minecolonies/core/colony/requestsystem/management/IStandardRequestManager.updateRequestState:(Lcom/minecolonies/api/colony/requestsystem/token/IToken;Lcom/minecolonies/api/colony/requestsystem/request/RequestState;)V
     160: return

  public void onRequestCompleted(com.minecolonies.api.colony.requestsystem.token.IToken<?>);
    Code:
       0: aload_0
       1: aload_1
       2: invokevirtual #155                // Method getRequest:(Lcom/minecolonies/api/colony/requestsystem/token/IToken;)Lcom/minecolonies/api/colony/requestsystem/request/IRequest;
       5: astore_2
       6: aload_2
       7: invokeinterface #418,  1          // InterfaceMethod com/minecolonies/api/colony/requestsystem/request/IRequest.getRequester:()Lcom/minecolonies/api/colony/requestsystem/requester/IRequester;
      12: aload_0
      13: getfield      #7                  // Field manager:Lcom/minecolonies/core/colony/requestsystem/management/IStandardRequestManager;
      16: aload_2
      17: invokeinterface #422,  3          // InterfaceMethod com/minecolonies/api/colony/requestsystem/requester/IRequester.onRequestedRequestComplete:(Lcom/minecolonies/api/colony/requestsystem/manager/IRequestManager;Lcom/minecolonies/api/colony/requestsystem/request/IRequest;)V
      22: aload_2
      23: invokeinterface #427,  1          // InterfaceMethod com/minecolonies/api/colony/requestsystem/request/IRequest.hasParent:()Z
      28: ifeq          138
      31: aload_0
      32: aload_2
      33: invokeinterface #430,  1          // InterfaceMethod com/minecolonies/api/colony/requestsystem/request/IRequest.getParent:()Lcom/minecolonies/api/colony/requestsystem/token/IToken;
      38: invokevirtual #155                // Method getRequest:(Lcom/minecolonies/api/colony/requestsystem/token/IToken;)Lcom/minecolonies/api/colony/requestsystem/request/IRequest;
      41: astore_3
      42: aload_0
      43: getfield      #7                  // Field manager:Lcom/minecolonies/core/colony/requestsystem/management/IStandardRequestManager;
      46: aload_2
      47: invokeinterface #90,  1           // InterfaceMethod com/minecolonies/api/colony/requestsystem/request/IRequest.getId:()Lcom/minecolonies/api/colony/requestsystem/token/IToken;
      52: getstatic     #433                // Field com/minecolonies/api/colony/requestsystem/request/RequestState.RECEIVED:Lcom/minecolonies/api/colony/requestsystem/request/RequestState;
      55: invokeinterface #373,  3          // InterfaceMethod com/minecolonies/core/colony/requestsystem/management/IStandardRequestManager.updateRequestState:(Lcom/minecolonies/api/colony/requestsystem/token/IToken;Lcom/minecolonies/api/colony/requestsystem/request/RequestState;)V
      60: aload_3
      61: aload_2
      62: invokeinterface #90,  1           // InterfaceMethod com/minecolonies/api/colony/requestsystem/request/IRequest.getId:()Lcom/minecolonies/api/colony/requestsystem/token/IToken;
      67: invokeinterface #436,  2          // InterfaceMethod com/minecolonies/api/colony/requestsystem/request/IRequest.removeChild:(Lcom/minecolonies/api/colony/requestsystem/token/IToken;)V
      72: aload_2
      73: aconst_null
      74: invokeinterface #318,  2          // InterfaceMethod com/minecolonies/api/colony/requestsystem/request/IRequest.setParent:(Lcom/minecolonies/api/colony/requestsystem/token/IToken;)V
      79: aload_3
      80: invokeinterface #336,  1          // InterfaceMethod com/minecolonies/api/colony/requestsystem/request/IRequest.hasChildren:()Z
      85: ifne          138
      88: aload_3
      89: invokeinterface #328,  1          // InterfaceMethod com/minecolonies/api/colony/requestsystem/request/IRequest.getState:()Lcom/minecolonies/api/colony/requestsystem/request/RequestState;
      94: getstatic     #333                // Field com/minecolonies/api/colony/requestsystem/request/RequestState.IN_PROGRESS:Lcom/minecolonies/api/colony/requestsystem/request/RequestState;
      97: if_acmpne     108
     100: aload_0
     101: aload_3
     102: invokevirtual #339                // Method resolveRequest:(Lcom/minecolonies/api/colony/requestsystem/request/IRequest;)V
     105: goto          138
     108: aload_3
     109: invokeinterface #328,  1          // InterfaceMethod com/minecolonies/api/colony/requestsystem/request/IRequest.getState:()Lcom/minecolonies/api/colony/requestsystem/request/RequestState;
     114: getstatic     #384                // Field com/minecolonies/api/colony/requestsystem/request/RequestState.FOLLOWUP_IN_PROGRESS:Lcom/minecolonies/api/colony/requestsystem/request/RequestState;
     117: if_acmpne     138
     120: aload_0
     121: getfield      #7                  // Field manager:Lcom/minecolonies/core/colony/requestsystem/management/IStandardRequestManager;
     124: aload_3
     125: invokeinterface #90,  1           // InterfaceMethod com/minecolonies/api/colony/requestsystem/request/IRequest.getId:()Lcom/minecolonies/api/colony/requestsystem/token/IToken;
     130: getstatic     #415                // Field com/minecolonies/api/colony/requestsystem/request/RequestState.COMPLETED:Lcom/minecolonies/api/colony/requestsystem/request/RequestState;
     133: invokeinterface #373,  3          // InterfaceMethod com/minecolonies/core/colony/requestsystem/management/IStandardRequestManager.updateRequestState:(Lcom/minecolonies/api/colony/requestsystem/token/IToken;Lcom/minecolonies/api/colony/requestsystem/request/RequestState;)V
     138: return

  public void onRequestOverruled(com.minecolonies.api.colony.requestsystem.token.IToken<?>);
    Code:
       0: aload_0
       1: aload_1
       2: invokevirtual #155                // Method getRequest:(Lcom/minecolonies/api/colony/requestsystem/token/IToken;)Lcom/minecolonies/api/colony/requestsystem/request/IRequest;
       5: astore_2
       6: aload_0
       7: getfield      #7                  // Field manager:Lcom/minecolonies/core/colony/requestsystem/management/IStandardRequestManager;
      10: invokeinterface #351,  1          // InterfaceMethod com/minecolonies/core/colony/requestsystem/management/IStandardRequestManager.getRequestResolverRequestAssignmentDataStore:()Lcom/minecolonies/api/colony/requestsystem/data/IRequestResolverRequestAssignmentDataStore;
      15: aload_1
      16: invokeinterface #377,  2          // InterfaceMethod com/minecolonies/api/colony/requestsystem/data/IRequestResolverRequestAssignmentDataStore.getAssignmentForValue:(Ljava/lang/Object;)Ljava/lang/Object;
      21: ifnonnull     46
      24: aload_0
      25: getfield      #7                  // Field manager:Lcom/minecolonies/core/colony/requestsystem/management/IStandardRequestManager;
      28: invokeinterface #81,  1           // InterfaceMethod com/minecolonies/core/colony/requestsystem/management/IStandardRequestManager.getRequestIdentitiesDataStore:()Lcom/minecolonies/api/colony/requestsystem/data/IRequestIdentitiesDataStore;
      33: invokeinterface #85,  1           // InterfaceMethod com/minecolonies/api/colony/requestsystem/data/IRequestIdentitiesDataStore.getIdentities:()Lcom/google/common/collect/BiMap;
      38: aload_1
      39: invokeinterface #439,  2          // InterfaceMethod com/google/common/collect/BiMap.remove:(Ljava/lang/Object;)Ljava/lang/Object;
      44: pop
      45: return
      46: aload_2
      47: invokeinterface #336,  1          // InterfaceMethod com/minecolonies/api/colony/requestsystem/request/IRequest.hasChildren:()Z
      52: ifeq          72
      55: aload_2
      56: invokeinterface #440,  1          // InterfaceMethod com/minecolonies/api/colony/requestsystem/request/IRequest.getChildren:()Lcom/google/common/collect/ImmutableCollection;
      61: astore_3
      62: aload_3
      63: aload_0
      64: invokedynamic #444,  0            // InvokeDynamic #10:accept:(Lcom/minecolonies/core/colony/requestsystem/management/handlers/RequestHandler;)Ljava/util/function/Consumer;
      69: invokevirtual #445                // Method com/google/common/collect/ImmutableCollection.forEach:(Ljava/util/function/Consumer;)V
      72: aload_0
      73: getfield      #7                  // Field manager:Lcom/minecolonies/core/colony/requestsystem/management/IStandardRequestManager;
      76: invokeinterface #221,  1          // InterfaceMethod com/minecolonies/core/colony/requestsystem/management/IStandardRequestManager.getResolverHandler:()Lcom/minecolonies/api/colony/requestsystem/management/IResolverHandler;
      81: aload_1
      82: invokeinterface #380,  2          // InterfaceMethod com/minecolonies/api/colony/requestsystem/management/IResolverHandler.getResolverForRequest:(Lcom/minecolonies/api/colony/requestsystem/token/IToken;)Lcom/minecolonies/api/colony/requestsystem/resolver/IRequestResolver;
      87: astore_3
      88: aload_3
      89: aload_0
      90: getfield      #7                  // Field manager:Lcom/minecolonies/core/colony/requestsystem/management/IStandardRequestManager;
      93: aload_2
      94: invokeinterface #347,  3          // InterfaceMethod com/minecolonies/api/colony/requestsystem/resolver/IRequestResolver.onAssignedRequestBeingCancelled:(Lcom/minecolonies/api/colony/requestsystem/manager/IRequestManager;Lcom/minecolonies/api/colony/requestsystem/request/IRequest;)V
      99: aload_0
     100: getfield      #7                  // Field manager:Lcom/minecolonies/core/colony/requestsystem/management/IStandardRequestManager;
     103: aload_1
     104: getstatic     #415                // Field com/minecolonies/api/colony/requestsystem/request/RequestState.COMPLETED:Lcom/minecolonies/api/colony/requestsystem/request/RequestState;
     107: invokeinterface #373,  3          // InterfaceMethod com/minecolonies/core/colony/requestsystem/management/IStandardRequestManager.updateRequestState:(Lcom/minecolonies/api/colony/requestsystem/token/IToken;Lcom/minecolonies/api/colony/requestsystem/request/RequestState;)V
     112: aload_3
     113: aload_0
     114: getfield      #7                  // Field manager:Lcom/minecolonies/core/colony/requestsystem/management/IStandardRequestManager;
     117: aload_2
     118: invokeinterface #367,  3          // InterfaceMethod com/minecolonies/api/colony/requestsystem/resolver/IRequestResolver.onAssignedRequestCancelled:(Lcom/minecolonies/api/colony/requestsystem/manager/IRequestManager;Lcom/minecolonies/api/colony/requestsystem/request/IRequest;)V
     123: return

  public void onRequestCancelled(com.minecolonies.api.colony.requestsystem.token.IToken<?>);
    Code:
       0: aload_0
       1: getfield      #7                  // Field manager:Lcom/minecolonies/core/colony/requestsystem/management/IStandardRequestManager;
       4: invokeinterface #311,  1          // InterfaceMethod com/minecolonies/core/colony/requestsystem/management/IStandardRequestManager.getRequestHandler:()Lcom/minecolonies/api/colony/requestsystem/management/IRequestHandler;
       9: aload_1
      10: invokeinterface #315,  2          // InterfaceMethod com/minecolonies/api/colony/requestsystem/management/IRequestHandler.getRequest:(Lcom/minecolonies/api/colony/requestsystem/token/IToken;)Lcom/minecolonies/api/colony/requestsystem/request/IRequest;
      15: astore_2
      16: aload_2
      17: ifnonnull     21
      20: return
      21: aload_2
      22: invokeinterface #427,  1          // InterfaceMethod com/minecolonies/api/colony/requestsystem/request/IRequest.hasParent:()Z
      27: ifeq          38
      30: aload_0
      31: aload_1
      32: invokevirtual #448                // Method onChildRequestCancelled:(Lcom/minecolonies/api/colony/requestsystem/token/IToken;)V
      35: goto          43
      38: aload_0
      39: aload_1
      40: invokevirtual #451                // Method onRequestCancelledDirectly:(Lcom/minecolonies/api/colony/requestsystem/token/IToken;)V
      43: aload_0
      44: getfield      #7                  // Field manager:Lcom/minecolonies/core/colony/requestsystem/management/IStandardRequestManager;
      47: invokeinterface #454,  1          // InterfaceMethod com/minecolonies/core/colony/requestsystem/management/IStandardRequestManager.markDirty:()V
      52: return

  public void onChildRequestCancelled(com.minecolonies.api.colony.requestsystem.token.IToken<?>);
    Code:
       0: aload_0
       1: getfield      #7                  // Field manager:Lcom/minecolonies/core/colony/requestsystem/management/IStandardRequestManager;
       4: aload_1
       5: invokeinterface #457,  2          // InterfaceMethod com/minecolonies/core/colony/requestsystem/management/IStandardRequestManager.getRequestForToken:(Lcom/minecolonies/api/colony/requestsystem/token/IToken;)Lcom/minecolonies/api/colony/requestsystem/request/IRequest;
      10: astore_2
      11: aload_0
      12: getfield      #7                  // Field manager:Lcom/minecolonies/core/colony/requestsystem/management/IStandardRequestManager;
      15: aload_2
      16: invokeinterface #430,  1          // InterfaceMethod com/minecolonies/api/colony/requestsystem/request/IRequest.getParent:()Lcom/minecolonies/api/colony/requestsystem/token/IToken;
      21: invokeinterface #457,  2          // InterfaceMethod com/minecolonies/core/colony/requestsystem/management/IStandardRequestManager.getRequestForToken:(Lcom/minecolonies/api/colony/requestsystem/token/IToken;)Lcom/minecolonies/api/colony/requestsystem/request/IRequest;
      26: astore_3
      27: aload_3
      28: invokeinterface #460,  1          // InterfaceMethod com/minecolonies/api/colony/requestsystem/request/IRequest.resetDeliveries:()V
      33: aload_3
      34: invokeinterface #440,  1          // InterfaceMethod com/minecolonies/api/colony/requestsystem/request/IRequest.getChildren:()Lcom/google/common/collect/ImmutableCollection;
      39: aload_0
      40: invokedynamic #444,  0            // InvokeDynamic #10:accept:(Lcom/minecolonies/core/colony/requestsystem/management/handlers/RequestHandler;)Ljava/util/function/Consumer;
      45: invokevirtual #445                // Method com/google/common/collect/ImmutableCollection.forEach:(Ljava/util/function/Consumer;)V
      48: aload_0
      49: aload_3
      50: invokestatic  #463                // Method com/google/common/collect/ImmutableList.of:()Lcom/google/common/collect/ImmutableList;
      53: invokevirtual #468                // Method reassignRequest:(Lcom/minecolonies/api/colony/requestsystem/request/IRequest;Ljava/util/Collection;)Lcom/minecolonies/api/colony/requestsystem/token/IToken;
      56: pop
      57: return

  public void onRequestCancelledDirectly(com.minecolonies.api.colony.requestsystem.token.IToken<?>);
    Code:
       0: aload_0
       1: getfield      #7                  // Field manager:Lcom/minecolonies/core/colony/requestsystem/management/IStandardRequestManager;
       4: aload_1
       5: invokeinterface #457,  2          // InterfaceMethod com/minecolonies/core/colony/requestsystem/management/IStandardRequestManager.getRequestForToken:(Lcom/minecolonies/api/colony/requestsystem/token/IToken;)Lcom/minecolonies/api/colony/requestsystem/request/IRequest;
      10: astore_2
      11: aload_2
      12: invokeinterface #336,  1          // InterfaceMethod com/minecolonies/api/colony/requestsystem/request/IRequest.hasChildren:()Z
      17: ifeq          35
      20: aload_2
      21: invokeinterface #440,  1          // InterfaceMethod com/minecolonies/api/colony/requestsystem/request/IRequest.getChildren:()Lcom/google/common/collect/ImmutableCollection;
      26: aload_0
      27: invokedynamic #444,  0            // InvokeDynamic #10:accept:(Lcom/minecolonies/core/colony/requestsystem/management/handlers/RequestHandler;)Ljava/util/function/Consumer;
      32: invokevirtual #445                // Method com/google/common/collect/ImmutableCollection.forEach:(Ljava/util/function/Consumer;)V
      35: aload_0
      36: aload_2
      37: invokevirtual #471                // Method processDirectCancellationAndNotifyRequesterOf:(Lcom/minecolonies/api/colony/requestsystem/request/IRequest;)V
      40: aload_0
      41: aload_1
      42: invokevirtual #474                // Method cleanRequestData:(Lcom/minecolonies/api/colony/requestsystem/token/IToken;)V
      45: return

  public void processDirectCancellationAndNotifyRequesterOf(com.minecolonies.api.colony.requestsystem.request.IRequest<?>);
    Code:
       0: aload_0
       1: aload_1
       2: invokevirtual #477                // Method processDirectCancellationOf:(Lcom/minecolonies/api/colony/requestsystem/request/IRequest;)V
       5: aload_1
       6: invokeinterface #418,  1          // InterfaceMethod com/minecolonies/api/colony/requestsystem/request/IRequest.getRequester:()Lcom/minecolonies/api/colony/requestsystem/requester/IRequester;
      11: aload_0
      12: getfield      #7                  // Field manager:Lcom/minecolonies/core/colony/requestsystem/management/IStandardRequestManager;
      15: aload_1
      16: invokeinterface #480,  3          // InterfaceMethod com/minecolonies/api/colony/requestsystem/requester/IRequester.onRequestedRequestCancelled:(Lcom/minecolonies/api/colony/requestsystem/manager/IRequestManager;Lcom/minecolonies/api/colony/requestsystem/request/IRequest;)V
      21: return

  public void processDirectCancellationOf(com.minecolonies.api.colony.requestsystem.request.IRequest<?>);
    Code:
       0: aload_0
       1: aload_1
       2: invokeinterface #90,  1           // InterfaceMethod com/minecolonies/api/colony/requestsystem/request/IRequest.getId:()Lcom/minecolonies/api/colony/requestsystem/token/IToken;
       7: invokevirtual #325                // Method isAssigned:(Lcom/minecolonies/api/colony/requestsystem/token/IToken;)Z
      10: istore_2
      11: aconst_null
      12: astore_3
      13: iload_2
      14: ifeq          181
      17: aload_0
      18: getfield      #7                  // Field manager:Lcom/minecolonies/core/colony/requestsystem/management/IStandardRequestManager;
      21: aload_1
      22: invokeinterface #90,  1           // InterfaceMethod com/minecolonies/api/colony/requestsystem/request/IRequest.getId:()Lcom/minecolonies/api/colony/requestsystem/token/IToken;
      27: invokeinterface #344,  2          // InterfaceMethod com/minecolonies/core/colony/requestsystem/management/IStandardRequestManager.getResolverForRequest:(Lcom/minecolonies/api/colony/requestsystem/token/IToken;)Lcom/minecolonies/api/colony/requestsystem/resolver/IRequestResolver;
      32: astore_3
      33: aload_3
      34: new           #160                // class com/minecolonies/core/colony/requestsystem/management/manager/wrapped/WrappedStaticStateRequestManager
      37: dup
      38: aload_0
      39: getfield      #7                  // Field manager:Lcom/minecolonies/core/colony/requestsystem/management/IStandardRequestManager;
      42: invokespecial #162                // Method com/minecolonies/core/colony/requestsystem/management/manager/wrapped/WrappedStaticStateRequestManager."<init>":(Lcom/minecolonies/core/colony/requestsystem/management/IStandardRequestManager;)V
      45: aload_1
      46: invokeinterface #347,  3          // InterfaceMethod com/minecolonies/api/colony/requestsystem/resolver/IRequestResolver.onAssignedRequestBeingCancelled:(Lcom/minecolonies/api/colony/requestsystem/manager/IRequestManager;Lcom/minecolonies/api/colony/requestsystem/request/IRequest;)V
      51: aload_0
      52: getfield      #7                  // Field manager:Lcom/minecolonies/core/colony/requestsystem/management/IStandardRequestManager;
      55: invokeinterface #351,  1          // InterfaceMethod com/minecolonies/core/colony/requestsystem/management/IStandardRequestManager.getRequestResolverRequestAssignmentDataStore:()Lcom/minecolonies/api/colony/requestsystem/data/IRequestResolverRequestAssignmentDataStore;
      60: invokeinterface #355,  1          // InterfaceMethod com/minecolonies/api/colony/requestsystem/data/IRequestResolverRequestAssignmentDataStore.getAssignments:()Ljava/util/Map;
      65: aload_3
      66: invokeinterface #271,  1          // InterfaceMethod com/minecolonies/api/colony/requestsystem/resolver/IRequestResolver.getId:()Lcom/minecolonies/api/colony/requestsystem/token/IToken;
      71: invokeinterface #358,  2          // InterfaceMethod java/util/Map.containsKey:(Ljava/lang/Object;)Z
      76: ifeq          181
      79: aload_0
      80: getfield      #7                  // Field manager:Lcom/minecolonies/core/colony/requestsystem/management/IStandardRequestManager;
      83: invokeinterface #351,  1          // InterfaceMethod com/minecolonies/core/colony/requestsystem/management/IStandardRequestManager.getRequestResolverRequestAssignmentDataStore:()Lcom/minecolonies/api/colony/requestsystem/data/IRequestResolverRequestAssignmentDataStore;
      88: invokeinterface #355,  1          // InterfaceMethod com/minecolonies/api/colony/requestsystem/data/IRequestResolverRequestAssignmentDataStore.getAssignments:()Ljava/util/Map;
      93: aload_3
      94: invokeinterface #271,  1          // InterfaceMethod com/minecolonies/api/colony/requestsystem/resolver/IRequestResolver.getId:()Lcom/minecolonies/api/colony/requestsystem/token/IToken;
      99: invokeinterface #213,  2          // InterfaceMethod java/util/Map.get:(Ljava/lang/Object;)Ljava/lang/Object;
     104: checkcast     #216                // class java/util/Collection
     107: aload_1
     108: invokeinterface #90,  1           // InterfaceMethod com/minecolonies/api/colony/requestsystem/request/IRequest.getId:()Lcom/minecolonies/api/colony/requestsystem/token/IToken;
     113: invokeinterface #359,  2          // InterfaceMethod java/util/Collection.remove:(Ljava/lang/Object;)Z
     118: pop
     119: aload_0
     120: getfield      #7                  // Field manager:Lcom/minecolonies/core/colony/requestsystem/management/IStandardRequestManager;
     123: invokeinterface #351,  1          // InterfaceMethod com/minecolonies/core/colony/requestsystem/management/IStandardRequestManager.getRequestResolverRequestAssignmentDataStore:()Lcom/minecolonies/api/colony/requestsystem/data/IRequestResolverRequestAssignmentDataStore;
     128: invokeinterface #355,  1          // InterfaceMethod com/minecolonies/api/colony/requestsystem/data/IRequestResolverRequestAssignmentDataStore.getAssignments:()Ljava/util/Map;
     133: aload_3
     134: invokeinterface #271,  1          // InterfaceMethod com/minecolonies/api/colony/requestsystem/resolver/IRequestResolver.getId:()Lcom/minecolonies/api/colony/requestsystem/token/IToken;
     139: invokeinterface #213,  2          // InterfaceMethod java/util/Map.get:(Ljava/lang/Object;)Ljava/lang/Object;
     144: checkcast     #216                // class java/util/Collection
     147: invokeinterface #362,  1          // InterfaceMethod java/util/Collection.isEmpty:()Z
     152: ifeq          181
     155: aload_0
     156: getfield      #7                  // Field manager:Lcom/minecolonies/core/colony/requestsystem/management/IStandardRequestManager;
     159: invokeinterface #351,  1          // InterfaceMethod com/minecolonies/core/colony/requestsystem/management/IStandardRequestManager.getRequestResolverRequestAssignmentDataStore:()Lcom/minecolonies/api/colony/requestsystem/data/IRequestResolverRequestAssignmentDataStore;
     164: invokeinterface #355,  1          // InterfaceMethod com/minecolonies/api/colony/requestsystem/data/IRequestResolverRequestAssignmentDataStore.getAssignments:()Ljava/util/Map;
     169: aload_3
     170: invokeinterface #271,  1          // InterfaceMethod com/minecolonies/api/colony/requestsystem/resolver/IRequestResolver.getId:()Lcom/minecolonies/api/colony/requestsystem/token/IToken;
     175: invokeinterface #365,  2          // InterfaceMethod java/util/Map.remove:(Ljava/lang/Object;)Ljava/lang/Object;
     180: pop
     181: aload_1
     182: invokeinterface #427,  1          // InterfaceMethod com/minecolonies/api/colony/requestsystem/request/IRequest.hasParent:()Z
     187: ifeq          211
     190: aload_0
     191: aload_1
     192: invokeinterface #430,  1          // InterfaceMethod com/minecolonies/api/colony/requestsystem/request/IRequest.getParent:()Lcom/minecolonies/api/colony/requestsystem/token/IToken;
     197: invokevirtual #155                // Method getRequest:(Lcom/minecolonies/api/colony/requestsystem/token/IToken;)Lcom/minecolonies/api/colony/requestsystem/request/IRequest;
     200: aload_1
     201: invokeinterface #90,  1           // InterfaceMethod com/minecolonies/api/colony/requestsystem/request/IRequest.getId:()Lcom/minecolonies/api/colony/requestsystem/token/IToken;
     206: invokeinterface #436,  2          // InterfaceMethod com/minecolonies/api/colony/requestsystem/request/IRequest.removeChild:(Lcom/minecolonies/api/colony/requestsystem/token/IToken;)V
     211: aload_1
     212: aconst_null
     213: invokeinterface #318,  2          // InterfaceMethod com/minecolonies/api/colony/requestsystem/request/IRequest.setParent:(Lcom/minecolonies/api/colony/requestsystem/token/IToken;)V
     218: aload_1
     219: aload_0
     220: getfield      #7                  // Field manager:Lcom/minecolonies/core/colony/requestsystem/management/IStandardRequestManager;
     223: getstatic     #483                // Field com/minecolonies/api/colony/requestsystem/request/RequestState.CANCELLED:Lcom/minecolonies/api/colony/requestsystem/request/RequestState;
     226: invokeinterface #171,  3          // InterfaceMethod com/minecolonies/api/colony/requestsystem/request/IRequest.setState:(Lcom/minecolonies/api/colony/requestsystem/manager/IRequestManager;Lcom/minecolonies/api/colony/requestsystem/request/RequestState;)V
     231: iload_2
     232: ifeq          253
     235: aload_3
     236: new           #160                // class com/minecolonies/core/colony/requestsystem/management/manager/wrapped/WrappedStaticStateRequestManager
     239: dup
     240: aload_0
     241: getfield      #7                  // Field manager:Lcom/minecolonies/core/colony/requestsystem/management/IStandardRequestManager;
     244: invokespecial #162                // Method com/minecolonies/core/colony/requestsystem/management/manager/wrapped/WrappedStaticStateRequestManager."<init>":(Lcom/minecolonies/core/colony/requestsystem/management/IStandardRequestManager;)V
     247: aload_1
     248: invokeinterface #367,  3          // InterfaceMethod com/minecolonies/api/colony/requestsystem/resolver/IRequestResolver.onAssignedRequestCancelled:(Lcom/minecolonies/api/colony/requestsystem/manager/IRequestManager;Lcom/minecolonies/api/colony/requestsystem/request/IRequest;)V
     253: return

  public void resolveRequest(com.minecolonies.api.colony.requestsystem.request.IRequest<?>);
    Code:
       0: aload_0
       1: aload_1
       2: invokeinterface #90,  1           // InterfaceMethod com/minecolonies/api/colony/requestsystem/request/IRequest.getId:()Lcom/minecolonies/api/colony/requestsystem/token/IToken;
       7: invokevirtual #155                // Method getRequest:(Lcom/minecolonies/api/colony/requestsystem/token/IToken;)Lcom/minecolonies/api/colony/requestsystem/request/IRequest;
      10: pop
      11: aload_0
      12: aload_1
      13: invokeinterface #90,  1           // InterfaceMethod com/minecolonies/api/colony/requestsystem/request/IRequest.getId:()Lcom/minecolonies/api/colony/requestsystem/token/IToken;
      18: invokevirtual #325                // Method isAssigned:(Lcom/minecolonies/api/colony/requestsystem/token/IToken;)Z
      21: ifne          35
      24: new           #100                // class java/lang/IllegalArgumentException
      27: dup
      28: ldc_w         #486                // String The given request is not resolved
      31: invokespecial #104                // Method java/lang/IllegalArgumentException."<init>":(Ljava/lang/String;)V
      34: athrow
      35: aload_1
      36: invokeinterface #328,  1          // InterfaceMethod com/minecolonies/api/colony/requestsystem/request/IRequest.getState:()Lcom/minecolonies/api/colony/requestsystem/request/RequestState;
      41: getstatic     #333                // Field com/minecolonies/api/colony/requestsystem/request/RequestState.IN_PROGRESS:Lcom/minecolonies/api/colony/requestsystem/request/RequestState;
      44: if_acmpeq     75
      47: new           #100                // class java/lang/IllegalArgumentException
      50: dup
      51: getstatic     #333                // Field com/minecolonies/api/colony/requestsystem/request/RequestState.IN_PROGRESS:Lcom/minecolonies/api/colony/requestsystem/request/RequestState;
      54: invokestatic  #63                 // Method java/lang/String.valueOf:(Ljava/lang/Object;)Ljava/lang/String;
      57: aload_1
      58: invokeinterface #328,  1          // InterfaceMethod com/minecolonies/api/colony/requestsystem/request/IRequest.getState:()Lcom/minecolonies/api/colony/requestsystem/request/RequestState;
      63: invokestatic  #63                 // Method java/lang/String.valueOf:(Ljava/lang/Object;)Ljava/lang/String;
      66: invokedynamic #488,  0            // InvokeDynamic #11:makeConcatWithConstants:(Ljava/lang/String;Ljava/lang/String;)Ljava/lang/String;
      71: invokespecial #104                // Method java/lang/IllegalArgumentException."<init>":(Ljava/lang/String;)V
      74: athrow
      75: aload_1
      76: invokeinterface #336,  1          // InterfaceMethod com/minecolonies/api/colony/requestsystem/request/IRequest.hasChildren:()Z
      81: ifeq          95
      84: new           #100                // class java/lang/IllegalArgumentException
      87: dup
      88: ldc_w         #491                // String Cannot resolve request with open Children
      91: invokespecial #104                // Method java/lang/IllegalArgumentException."<init>":(Ljava/lang/String;)V
      94: athrow
      95: aload_0
      96: getfield      #7                  // Field manager:Lcom/minecolonies/core/colony/requestsystem/management/IStandardRequestManager;
      99: invokeinterface #221,  1          // InterfaceMethod com/minecolonies/core/colony/requestsystem/management/IStandardRequestManager.getResolverHandler:()Lcom/minecolonies/api/colony/requestsystem/management/IResolverHandler;
     104: aload_1
     105: invokeinterface #493,  2          // InterfaceMethod com/minecolonies/api/colony/requestsystem/management/IResolverHandler.getResolverForRequest:(Lcom/minecolonies/api/colony/requestsystem/request/IRequest;)Lcom/minecolonies/api/colony/requestsystem/resolver/IRequestResolver;
     110: astore_2
     111: aload_1
     112: new           #160                // class com/minecolonies/core/colony/requestsystem/management/manager/wrapped/WrappedStaticStateRequestManager
     115: dup
     116: aload_0
     117: getfield      #7                  // Field manager:Lcom/minecolonies/core/colony/requestsystem/management/IStandardRequestManager;
     120: invokespecial #162                // Method com/minecolonies/core/colony/requestsystem/management/manager/wrapped/WrappedStaticStateRequestManager."<init>":(Lcom/minecolonies/core/colony/requestsystem/management/IStandardRequestManager;)V
     123: getstatic     #333                // Field com/minecolonies/api/colony/requestsystem/request/RequestState.IN_PROGRESS:Lcom/minecolonies/api/colony/requestsystem/request/RequestState;
     126: invokeinterface #171,  3          // InterfaceMethod com/minecolonies/api/colony/requestsystem/request/IRequest.setState:(Lcom/minecolonies/api/colony/requestsystem/manager/IRequestManager;Lcom/minecolonies/api/colony/requestsystem/request/RequestState;)V
     131: aload_2
     132: aload_0
     133: getfield      #7                  // Field manager:Lcom/minecolonies/core/colony/requestsystem/management/IStandardRequestManager;
     136: aload_1
     137: invokeinterface #496,  3          // InterfaceMethod com/minecolonies/api/colony/requestsystem/resolver/IRequestResolver.resolveRequest:(Lcom/minecolonies/api/colony/requestsystem/manager/IRequestManager;Lcom/minecolonies/api/colony/requestsystem/request/IRequest;)V
     142: return

  public void cleanRequestData(com.minecolonies.api.colony.requestsystem.token.IToken<?>);
    Code:
       0: aload_0
       1: getfield      #7                  // Field manager:Lcom/minecolonies/core/colony/requestsystem/management/IStandardRequestManager;
       4: aload_1
       5: invokestatic  #63                 // Method java/lang/String.valueOf:(Ljava/lang/Object;)Ljava/lang/String;
       8: invokedynamic #498,  0            // InvokeDynamic #12:makeConcatWithConstants:(Ljava/lang/String;)Ljava/lang/String;
      13: invokeinterface #73,  2           // InterfaceMethod com/minecolonies/core/colony/requestsystem/management/IStandardRequestManager.log:(Ljava/lang/String;)V
      18: aload_0
      19: aload_1
      20: invokevirtual #155                // Method getRequest:(Lcom/minecolonies/api/colony/requestsystem/token/IToken;)Lcom/minecolonies/api/colony/requestsystem/request/IRequest;
      23: pop
      24: aload_0
      25: aload_1
      26: invokevirtual #325                // Method isAssigned:(Lcom/minecolonies/api/colony/requestsystem/token/IToken;)Z
      29: ifeq          145
      32: aload_0
      33: getfield      #7                  // Field manager:Lcom/minecolonies/core/colony/requestsystem/management/IStandardRequestManager;
      36: invokeinterface #221,  1          // InterfaceMethod com/minecolonies/core/colony/requestsystem/management/IStandardRequestManager.getResolverHandler:()Lcom/minecolonies/api/colony/requestsystem/management/IResolverHandler;
      41: aload_1
      42: invokeinterface #380,  2          // InterfaceMethod com/minecolonies/api/colony/requestsystem/management/IResolverHandler.getResolverForRequest:(Lcom/minecolonies/api/colony/requestsystem/token/IToken;)Lcom/minecolonies/api/colony/requestsystem/resolver/IRequestResolver;
      47: astore_2
      48: aload_0
      49: getfield      #7                  // Field manager:Lcom/minecolonies/core/colony/requestsystem/management/IStandardRequestManager;
      52: invokeinterface #351,  1          // InterfaceMethod com/minecolonies/core/colony/requestsystem/management/IStandardRequestManager.getRequestResolverRequestAssignmentDataStore:()Lcom/minecolonies/api/colony/requestsystem/data/IRequestResolverRequestAssignmentDataStore;
      57: invokeinterface #355,  1          // InterfaceMethod com/minecolonies/api/colony/requestsystem/data/IRequestResolverRequestAssignmentDataStore.getAssignments:()Ljava/util/Map;
      62: aload_2
      63: invokeinterface #271,  1          // InterfaceMethod com/minecolonies/api/colony/requestsystem/resolver/IRequestResolver.getId:()Lcom/minecolonies/api/colony/requestsystem/token/IToken;
      68: invokeinterface #213,  2          // InterfaceMethod java/util/Map.get:(Ljava/lang/Object;)Ljava/lang/Object;
      73: checkcast     #216                // class java/util/Collection
      76: aload_1
      77: invokeinterface #359,  2          // InterfaceMethod java/util/Collection.remove:(Ljava/lang/Object;)Z
      82: pop
      83: aload_0
      84: getfield      #7                  // Field manager:Lcom/minecolonies/core/colony/requestsystem/management/IStandardRequestManager;
      87: invokeinterface #351,  1          // InterfaceMethod com/minecolonies/core/colony/requestsystem/management/IStandardRequestManager.getRequestResolverRequestAssignmentDataStore:()Lcom/minecolonies/api/colony/requestsystem/data/IRequestResolverRequestAssignmentDataStore;
      92: invokeinterface #355,  1          // InterfaceMethod com/minecolonies/api/colony/requestsystem/data/IRequestResolverRequestAssignmentDataStore.getAssignments:()Ljava/util/Map;
      97: aload_2
      98: invokeinterface #271,  1          // InterfaceMethod com/minecolonies/api/colony/requestsystem/resolver/IRequestResolver.getId:()Lcom/minecolonies/api/colony/requestsystem/token/IToken;
     103: invokeinterface #213,  2          // InterfaceMethod java/util/Map.get:(Ljava/lang/Object;)Ljava/lang/Object;
     108: checkcast     #216                // class java/util/Collection
     111: invokeinterface #362,  1          // InterfaceMethod java/util/Collection.isEmpty:()Z
     116: ifeq          145
     119: aload_0
     120: getfield      #7                  // Field manager:Lcom/minecolonies/core/colony/requestsystem/management/IStandardRequestManager;
     123: invokeinterface #351,  1          // InterfaceMethod com/minecolonies/core/colony/requestsystem/management/IStandardRequestManager.getRequestResolverRequestAssignmentDataStore:()Lcom/minecolonies/api/colony/requestsystem/data/IRequestResolverRequestAssignmentDataStore;
     128: invokeinterface #355,  1          // InterfaceMethod com/minecolonies/api/colony/requestsystem/data/IRequestResolverRequestAssignmentDataStore.getAssignments:()Ljava/util/Map;
     133: aload_2
     134: invokeinterface #271,  1          // InterfaceMethod com/minecolonies/api/colony/requestsystem/resolver/IRequestResolver.getId:()Lcom/minecolonies/api/colony/requestsystem/token/IToken;
     139: invokeinterface #365,  2          // InterfaceMethod java/util/Map.remove:(Ljava/lang/Object;)Ljava/lang/Object;
     144: pop
     145: aload_0
     146: getfield      #7                  // Field manager:Lcom/minecolonies/core/colony/requestsystem/management/IStandardRequestManager;
     149: invokeinterface #81,  1           // InterfaceMethod com/minecolonies/core/colony/requestsystem/management/IStandardRequestManager.getRequestIdentitiesDataStore:()Lcom/minecolonies/api/colony/requestsystem/data/IRequestIdentitiesDataStore;
     154: invokeinterface #85,  1           // InterfaceMethod com/minecolonies/api/colony/requestsystem/data/IRequestIdentitiesDataStore.getIdentities:()Lcom/google/common/collect/BiMap;
     159: aload_1
     160: invokeinterface #439,  2          // InterfaceMethod com/google/common/collect/BiMap.remove:(Ljava/lang/Object;)Ljava/lang/Object;
     165: pop
     166: return

  public void removeRequester(com.minecolonies.api.colony.requestsystem.requester.IRequester);
    Code:
       0: new           #184                // class java/util/ArrayList
       3: dup
       4: aload_0
       5: getfield      #7                  // Field manager:Lcom/minecolonies/core/colony/requestsystem/management/IStandardRequestManager;
       8: invokeinterface #81,  1           // InterfaceMethod com/minecolonies/core/colony/requestsystem/management/IStandardRequestManager.getRequestIdentitiesDataStore:()Lcom/minecolonies/api/colony/requestsystem/data/IRequestIdentitiesDataStore;
      13: invokeinterface #85,  1           // InterfaceMethod com/minecolonies/api/colony/requestsystem/data/IRequestIdentitiesDataStore.getIdentities:()Lcom/google/common/collect/BiMap;
      18: invokeinterface #499,  1          // InterfaceMethod com/google/common/collect/BiMap.values:()Ljava/util/Set;
      23: invokespecial #502                // Method java/util/ArrayList."<init>":(Ljava/util/Collection;)V
      26: invokevirtual #503                // Method java/util/ArrayList.iterator:()Ljava/util/Iterator;
      29: astore_2
      30: aload_2
      31: invokeinterface #193,  1          // InterfaceMethod java/util/Iterator.hasNext:()Z
      36: ifeq          87
      39: aload_2
      40: invokeinterface #199,  1          // InterfaceMethod java/util/Iterator.next:()Ljava/lang/Object;
      45: checkcast     #61                 // class com/minecolonies/api/colony/requestsystem/request/IRequest
      48: astore_3
      49: aload_3
      50: invokeinterface #418,  1          // InterfaceMethod com/minecolonies/api/colony/requestsystem/request/IRequest.getRequester:()Lcom/minecolonies/api/colony/requestsystem/requester/IRequester;
      55: invokeinterface #504,  1          // InterfaceMethod com/minecolonies/api/colony/requestsystem/requester/IRequester.getId:()Lcom/minecolonies/api/colony/requestsystem/token/IToken;
      60: aload_1
      61: invokeinterface #504,  1          // InterfaceMethod com/minecolonies/api/colony/requestsystem/requester/IRequester.getId:()Lcom/minecolonies/api/colony/requestsystem/token/IToken;
      66: invokeinterface #505,  2          // InterfaceMethod com/minecolonies/api/colony/requestsystem/token/IToken.equals:(Ljava/lang/Object;)Z
      71: ifeq          84
      74: aload_0
      75: aload_3
      76: invokeinterface #90,  1           // InterfaceMethod com/minecolonies/api/colony/requestsystem/request/IRequest.getId:()Lcom/minecolonies/api/colony/requestsystem/token/IToken;
      81: invokevirtual #508                // Method onRequestCancelled:(Lcom/minecolonies/api/colony/requestsystem/token/IToken;)V
      84: goto          30
      87: return

  public com.minecolonies.api.colony.requestsystem.request.IRequest<?> getRequest(com.minecolonies.api.colony.requestsystem.token.IToken<?>);
    Code:
       0: aload_0
       1: getfield      #7                  // Field manager:Lcom/minecolonies/core/colony/requestsystem/management/IStandardRequestManager;
       4: invokeinterface #81,  1           // InterfaceMethod com/minecolonies/core/colony/requestsystem/management/IStandardRequestManager.getRequestIdentitiesDataStore:()Lcom/minecolonies/api/colony/requestsystem/data/IRequestIdentitiesDataStore;
       9: invokeinterface #85,  1           // InterfaceMethod com/minecolonies/api/colony/requestsystem/data/IRequestIdentitiesDataStore.getIdentities:()Lcom/google/common/collect/BiMap;
      14: aload_1
      15: invokeinterface #93,  2           // InterfaceMethod com/google/common/collect/BiMap.containsKey:(Ljava/lang/Object;)Z
      20: ifne          34
      23: new           #100                // class java/lang/IllegalArgumentException
      26: dup
      27: ldc_w         #511                // String The given token is not registered as a request to this manager
      30: invokespecial #104                // Method java/lang/IllegalArgumentException."<init>":(Ljava/lang/String;)V
      33: athrow
      34: aload_0
      35: aload_1
      36: invokevirtual #513                // Method getRequestOrNull:(Lcom/minecolonies/api/colony/requestsystem/token/IToken;)Lcom/minecolonies/api/colony/requestsystem/request/IRequest;
      39: areturn

  public com.minecolonies.api.colony.requestsystem.request.IRequest<?> getRequestOrNull(com.minecolonies.api.colony.requestsystem.token.IToken<?>);
    Code:
       0: aload_0
       1: getfield      #7                  // Field manager:Lcom/minecolonies/core/colony/requestsystem/management/IStandardRequestManager;
       4: invokeinterface #81,  1           // InterfaceMethod com/minecolonies/core/colony/requestsystem/management/IStandardRequestManager.getRequestIdentitiesDataStore:()Lcom/minecolonies/api/colony/requestsystem/data/IRequestIdentitiesDataStore;
       9: invokeinterface #85,  1           // InterfaceMethod com/minecolonies/api/colony/requestsystem/data/IRequestIdentitiesDataStore.getIdentities:()Lcom/google/common/collect/BiMap;
      14: aload_1
      15: invokeinterface #41,  2           // InterfaceMethod com/google/common/collect/BiMap.get:(Ljava/lang/Object;)Ljava/lang/Object;
      20: checkcast     #61                 // class com/minecolonies/api/colony/requestsystem/request/IRequest
      23: areturn

  public java.util.Collection<com.minecolonies.api.colony.requestsystem.request.IRequest<?>> getRequestsMadeByRequester(com.minecolonies.api.colony.requestsystem.requester.IRequester);
    Code:
       0: aload_0
       1: getfield      #7                  // Field manager:Lcom/minecolonies/core/colony/requestsystem/management/IStandardRequestManager;
       4: invokeinterface #81,  1           // InterfaceMethod com/minecolonies/core/colony/requestsystem/management/IStandardRequestManager.getRequestIdentitiesDataStore:()Lcom/minecolonies/api/colony/requestsystem/data/IRequestIdentitiesDataStore;
       9: invokeinterface #85,  1           // InterfaceMethod com/minecolonies/api/colony/requestsystem/data/IRequestIdentitiesDataStore.getIdentities:()Lcom/google/common/collect/BiMap;
      14: invokeinterface #499,  1          // InterfaceMethod com/google/common/collect/BiMap.values:()Ljava/util/Set;
      19: invokeinterface #516,  1          // InterfaceMethod java/util/Set.stream:()Ljava/util/stream/Stream;
      24: aload_1
      25: invokedynamic #517,  0            // InvokeDynamic #13:test:(Lcom/minecolonies/api/colony/requestsystem/requester/IRequester;)Ljava/util/function/Predicate;
      30: invokeinterface #405,  2          // InterfaceMethod java/util/stream/Stream.filter:(Ljava/util/function/Predicate;)Ljava/util/stream/Stream;
      35: invokestatic  #520                // Method java/util/stream/Collectors.toList:()Ljava/util/stream/Collector;
      38: invokeinterface #526,  2          // InterfaceMethod java/util/stream/Stream.collect:(Ljava/util/stream/Collector;)Ljava/lang/Object;
      43: checkcast     #216                // class java/util/Collection
      46: areturn
}
